<?xml version="1.0" ?>
<State><Center ID = "SAHB">
<Dispatch ID = "SACC">

		<Log ID = "220120SA00099">
			<LogTime>"Jan 20 2022  5:21AM"</LogTime>
			<LogType>"1179-Trfc Collision-1141 Enrt"</LogType>
			<Location>"Watt Ave / Arden Way"</Location>
			<LocationDesc>"SB JSO"</LocationDesc>
			<Area>"North Sac"</Area>
			<ThomasBrothers>""</ThomasBrothers>
			<LATLON>"38595789:121382892"</LATLON>
			<LogDetails>
		<details>
			<DetailTime>"Jan 20 2022  5:23AM"</DetailTime>
			<IncidentDetail>"[16] VEH ON SIDEWALK"</IncidentDetail>
		</details>
		<details>
			<DetailTime>"Jan 20 2022  5:22AM"</DetailTime>
			<IncidentDetail>"[8] [Appended, 05:23:10] [3] WIRES ARE 1125"</IncidentDetail>
		</details>
		<details>
			<DetailTime>"Jan 20 2022  5:22AM"</DetailTime>
			<IncidentDetail>"[4] TRAFFIC LIGHTS OUT AT I/S"</IncidentDetail>
		</details>
		<details>
			<DetailTime>"Jan 20 2022  5:22AM"</DetailTime>
			<IncidentDetail>"[7] [Appended, 05:23:10] [2] UNK COL TKPK VS POLE"</IncidentDetail>
		</details>
		<details>
			<DetailTime>"Jan 20 2022  5:22AM"</DetailTime>
			<IncidentDetail>"[14] [Appended, 05:23:24] [4] NEG 1125"</IncidentDetail>
		</details>
		<details>
			<DetailTime>"Jan 20 2022  5:22AM"</DetailTime>
			<IncidentDetail>"[3] POLE DOWN // SPARKING"</IncidentDetail>
		</details>
		<details>
			<DetailTime>"Jan 20 2022  5:22AM"</DetailTime>
			<IncidentDetail>"[12] [Appended, 05:23:24] [2] VEH NOW INTO A YARD"</IncidentDetail>
		</details>
		<details>
			<DetailTime>"Jan 20 2022  5:22AM"</DetailTime>
			<IncidentDetail>"[11] [Appended, 05:23:24] [1] FORD TK   VS   POLE"</IncidentDetail>
		</details>
		<details>
			<DetailTime>"Jan 20 2022  5:21AM"</DetailTime>
			<IncidentDetail>"[1] VEH VS POLE"</IncidentDetail>
		</details><units>
			<UnitTime>"Jan 20 2022  5:24AM"</UnitTime>
			<UnitDetail>"Unit Enroute"</UnitDetail></units><units>
			<UnitTime>"Jan 20 2022  5:24AM"</UnitTime>
			<UnitDetail>"Unit Assigned"</UnitDetail></units><units>
			<UnitTime>"Jan 20 2022  5:23AM"</UnitTime>
			<UnitDetail>"Unit Assigned"</UnitDetail></units></LogDetails></Log>

		<Log ID = "220120SA00096">
			<LogTime>"Jan 20 2022  5:15AM"</LogTime>
			<LogType>"20002-Hit and Run No Injuries"</LogType>
			<Location>"3838 49th Ave"</Location>
			<LocationDesc>"LOON HING CO"</LocationDesc>
			<Area>"South Sac"</Area>
			<ThomasBrothers>""</ThomasBrothers>
			<LATLON>"38506338:121463891"</LATLON>
			<LogDetails>
		<details>
			<DetailTime>"Jan 20 2022  5:18AM"</DetailTime>
			<IncidentDetail>"[3] DEBRI IN RDWY"</IncidentDetail>
		</details><units>
			<UnitTime>"Jan 20 2022  5:21AM"</UnitTime>
			<UnitDetail>"Unit Enroute"</UnitDetail></units><units>
			<UnitTime>"Jan 20 2022  5:21AM"</UnitTime>
			<UnitDetail>"Unit Assigned"</UnitDetail></units></LogDetails></Log>

		<Log ID = "220120SA00088">
			<LogTime>"Jan 20 2022  5:01AM"</LogTime>
			<LogType>"1166-Defective Traffic Signals"</LogType>
			<Location>"Calvine Rd / Vintage Park Dr"</Location>
			<LocationDesc>""</LocationDesc>
			<Area>"South Sac"</Area>
			<ThomasBrothers>""</ThomasBrothers>
			<LATLON>"38452532:121378165"</LATLON>
			<LogDetails>
		<details>
			<DetailTime>"Jan 20 2022  5:17AM"</DetailTime>
			<IncidentDetail>"[6] Incident Re-opened:  PER ANOTHER VEHS TURNING AROUND AND GOING WW "</IncidentDetail>
		</details>
		<details>
			<DetailTime>"Jan 20 2022  5:04AM"</DetailTime>
			<IncidentDetail>"[5] 1039 UPRR"</IncidentDetail>
		</details></LogDetails></Log>

		<Log ID = "220119SA01063">
			<LogTime>"Jan 19 2022  6:29PM"</LogTime>
			<LogType>"CZP-Assist with Construction"</LogType>
			<Location>"I80 W / Bryte Bend Bridge Bbb"</Location>
			<LocationDesc>"I80 W / BBB"</LocationDesc>
			<Area>"North Sac"</Area>
			<ThomasBrothers>""</ThomasBrothers>
			<LATLON>"38598669:121547869"</LATLON>
			<LogDetails><details/><units>
			<UnitTime>"Jan 19 2022 10:17PM"</UnitTime>
			<UnitDetail>"Unit At Scene"</UnitDetail></units><units>
			<UnitTime>"Jan 19 2022 10:17PM"</UnitTime>
			<UnitDetail>"Unit Enroute"</UnitDetail></units><units>
			<UnitTime>"Jan 19 2022 10:17PM"</UnitTime>
			<UnitDetail>"Unit Assigned"</UnitDetail></units><units>
			<UnitTime>"Jan 20 2022  5:23AM"</UnitTime>
			<UnitDetail>"Unit Cleared"</UnitDetail></units><units>
			<UnitTime>"Jan 19 2022  9:57PM"</UnitTime>
			<UnitDetail>"Unit At Scene"</UnitDetail></units><units>
			<UnitTime>"Jan 19 2022  9:57PM"</UnitTime>
			<UnitDetail>"Unit Enroute"</UnitDetail></units><units>
			<UnitTime>"Jan 19 2022  9:57PM"</UnitTime>
			<UnitDetail>"Unit Assigned"</UnitDetail></units><units>
			<UnitTime>"Jan 19 2022 11:11PM"</UnitTime>
			<UnitDetail>"Unit Cleared"</UnitDetail></units><units>
			<UnitTime>"Jan 19 2022  9:49PM"</UnitTime>
			<UnitDetail>"Unit At Scene"</UnitDetail></units><units>
			<UnitTime>"Jan 19 2022  9:49PM"</UnitTime>
			<UnitDetail>"Unit Enroute"</UnitDetail></units><units>
			<UnitTime>"Jan 19 2022  9:49PM"</UnitTime>
			<UnitDetail>"Unit Assigned"</UnitDetail></units><units>
			<UnitTime>"Jan 19 2022  9:01PM"</UnitTime>
			<UnitDetail>"Unit Cleared"</UnitDetail></units><units>
			<UnitTime>"Jan 19 2022  7:46PM"</UnitTime>
			<UnitDetail>"Unit Enroute"</UnitDetail></units><units>
			<UnitTime>"Jan 19 2022  7:46PM"</UnitTime>
			<UnitDetail>"Unit Assigned"</UnitDetail></units><units>
			<UnitTime>"Jan 19 2022  9:04PM"</UnitTime>
			<UnitDetail>"Unit Cleared"</UnitDetail></units><units>
			<UnitTime>"Jan 19 2022  6:29PM"</UnitTime>
			<UnitDetail>"Unit At Scene"</UnitDetail></units><units>
			<UnitTime>"Jan 19 2022  6:29PM"</UnitTime>
			<UnitDetail>"Unit Enroute"</UnitDetail></units><units>
			<UnitTime>"Jan 19 2022  6:29PM"</UnitTime>
			<UnitDetail>"Unit Assigned"</UnitDetail></units></LogDetails></Log>
</Dispatch>
<Dispatch ID = "CHCC">

		<Log ID = "220120CH00010">
			<LogTime>"Jan 20 2022  5:13AM"</LogTime>
			<LogType>"CFIRE-Car Fire"</LogType>
			<Location>"2468 Tierra Buena Rd"</Location>
			<LocationDesc>""</LocationDesc>
			<Area>"Yuba Sutter"</Area>
			<ThomasBrothers>""</ThomasBrothers>
			<LATLON>"39165387:121662318"</LATLON>
			<LogDetails>
		<details>
			<DetailTime>"Jan 20 2022  5:16AM"</DetailTime>
			<IncidentDetail>"[7] 1039 OFC"</IncidentDetail>
		</details>
		<details>
			<DetailTime>"Jan 20 2022  5:14AM"</DetailTime>
			<IncidentDetail>"[6] L4 CITY ADVISED FOR FIRE"</IncidentDetail>
		</details>
		<details>
			<DetailTime>"Jan 20 2022  5:13AM"</DetailTime>
			<IncidentDetail>"[5] RHS"</IncidentDetail>
		</details>
		<details>
			<DetailTime>"Jan 20 2022  5:13AM"</DetailTime>
			<IncidentDetail>"[4] FIRE ADVISED FOR FIRE"</IncidentDetail>
		</details>
		<details>
			<DetailTime>"Jan 20 2022  5:13AM"</DetailTime>
			<IncidentDetail>"[1] BOAT ON FIRE"</IncidentDetail>
		</details><units>
			<UnitTime>"Jan 20 2022  5:19AM"</UnitTime>
			<UnitDetail>"Unit Enroute"</UnitDetail></units><units>
			<UnitTime>"Jan 20 2022  5:19AM"</UnitTime>
			<UnitDetail>"Unit Assigned"</UnitDetail></units></LogDetails></Log>

		<Log ID = "220120CH00007">
			<LogTime>"Jan 20 2022  3:42AM"</LogTime>
			<LogType>"1125-Traffic Hazard"</LogType>
			<Location>"70 Pepsi Way"</Location>
			<LocationDesc>""</LocationDesc>
			<Area>"Chico"</Area>
			<ThomasBrothers>""</ThomasBrothers>
			<LATLON>"39645298:121722272"</LATLON>
			<LogDetails>
		<details>
			<DetailTime>"Jan 20 2022  4:09AM"</DetailTime>
			<IncidentDetail>"[19] 1039 BCSO"</IncidentDetail>
		</details>
		<details>
			<DetailTime>"Jan 20 2022  3:47AM"</DetailTime>
			<IncidentDetail>"[14] 1039 OFC"</IncidentDetail>
		</details>
		<details>
			<DetailTime>"Jan 20 2022  3:44AM"</DetailTime>
			<IncidentDetail>"[11] REQ VEH TO BE MOVED WILL NEED AREA TO START FILLING UP WORK TRUCKS"</IncidentDetail>
		</details>
		<details>
			<DetailTime>"Jan 20 2022  3:43AM"</DetailTime>
			<IncidentDetail>"[8] VEH STILL 97 BLOCKING"</IncidentDetail>
		</details>
		<details>
			<DetailTime>"Jan 20 2022  3:42AM"</DetailTime>
			<IncidentDetail>"[5] VEH RAN OO GAS AT PUMPS"</IncidentDetail>
		</details>
		<details>
			<DetailTime>"Jan 20 2022  3:42AM"</DetailTime>
			<IncidentDetail>"[4] 1126 IS 1125"</IncidentDetail>
		</details><units>
			<UnitTime>"Jan 20 2022  4:06AM"</UnitTime>
			<UnitDetail>"Unit At Scene"</UnitDetail></units><units>
			<UnitTime>"Jan 20 2022  3:59AM"</UnitTime>
			<UnitDetail>"Unit Enroute"</UnitDetail></units><units>
			<UnitTime>"Jan 20 2022  3:59AM"</UnitTime>
			<UnitDetail>"Unit Assigned"</UnitDetail></units><units>
			<UnitTime>"Jan 20 2022  4:06AM"</UnitTime>
			<UnitDetail>"Unit At Scene"</UnitDetail></units><units>
			<UnitTime>"Jan 20 2022  3:54AM"</UnitTime>
			<UnitDetail>"Unit Enroute"</UnitDetail></units><units>
			<UnitTime>"Jan 20 2022  3:54AM"</UnitTime>
			<UnitDetail>"Unit Assigned"</UnitDetail></units></LogDetails></Log>
</Dispatch>
<Dispatch ID = "TKCC">

		<Log ID = "220120TK00001">
			<LogTime>"Jan 20 2022 12:27AM"</LogTime>
			<LogType>"CLOSURE-Closure of a Road"</LogType>
			<Location>"2063 Hopi Ave"</Location>
			<LocationDesc>"** CLOSURES 1/20 **"</LocationDesc>
			<Area>"South Lake"</Area>
			<ThomasBrothers>""</ThomasBrothers>
			<LATLON>"38853533:120019154"</LATLON>
			<LogDetails>
		<details>
			<DetailTime>"Jan 20 2022 12:27AM"</DetailTime>
			<IncidentDetail>"[2] ^SR89 AT MONITOR PASS"</IncidentDetail>
		</details>
		<details>
			<DetailTime>"Jan 20 2022 12:27AM"</DetailTime>
			<IncidentDetail>"[1] ^SR4 AT EBBETTS PASS"</IncidentDetail>
		</details></LogDetails></Log>
</Dispatch>
</Center>

<Center ID = "GGHB">
<Dispatch ID = "GGCC">

		<Log ID = "220120GG00213">
			<LogTime>"Jan 20 2022  5:11AM"</LogTime>
			<LogType>"FIRE-Report of Fire"</LogType>
			<Location>"I880 N / High St Ofr"</Location>
			<LocationDesc>"NB 880  JNO HIGH"</LocationDesc>
			<Area>"Oakland"</Area>
			<ThomasBrothers>""</ThomasBrothers>
			<LATLON>"37764023:122216843"</LATLON>
			<LogDetails>
		<details>
			<DetailTime>"Jan 20 2022  5:14AM"</DetailTime>
			<IncidentDetail>"[5] 1039 OFC"</IncidentDetail>
		</details>
		<details>
			<DetailTime>"Jan 20 2022  5:12AM"</DetailTime>
			<IncidentDetail>"[3] XFER  FIRE"</IncidentDetail>
		</details>
		<details>
			<DetailTime>"Jan 20 2022  5:11AM"</DetailTime>
			<IncidentDetail>"[2] POSS GRASS ON FIRE"</IncidentDetail>
		</details></LogDetails></Log>

		<Log ID = "220120GG00192">
			<LogTime>"Jan 20 2022  4:34AM"</LogTime>
			<LogType>"FOG-Foggy Conditions"</LogType>
			<Location>"Us101 S"</Location>
			<LocationDesc>"GGB * FOG ADV"</LocationDesc>
			<Area>"Marin"</Area>
			<ThomasBrothers>""</ThomasBrothers>
			<LATLON>"37825615:122479262"</LATLON>
			<LogDetails><details/><units>
			<UnitTime>"Jan 20 2022  4:35AM"</UnitTime>
			<UnitDetail>"Unit At Scene"</UnitDetail></units><units>
			<UnitTime>"Jan 20 2022  4:35AM"</UnitTime>
			<UnitDetail>"Unit Assigned"</UnitDetail></units></LogDetails></Log>

		<Log ID = "220120GG00188">
			<LogTime>"Jan 20 2022  4:32AM"</LogTime>
			<LogType>"CZP-Assist with Construction"</LogType>
			<Location>"0 I580 E"</Location>
			<LocationDesc>"EB 580 Richmond-San Rafael Brg"</LocationDesc>
			<Area>"Marin"</Area>
			<ThomasBrothers>""</ThomasBrothers>
			<LATLON>"37942505:122477783"</LATLON>
			<LogDetails><details/><units>
			<UnitTime>"Jan 20 2022  4:32AM"</UnitTime>
			<UnitDetail>"Unit At Scene"</UnitDetail></units><units>
			<UnitTime>"Jan 20 2022  4:32AM"</UnitTime>
			<UnitDetail>"Unit Enroute"</UnitDetail></units><units>
			<UnitTime>"Jan 20 2022  4:32AM"</UnitTime>
			<UnitDetail>"Unit Assigned"</UnitDetail></units></LogDetails></Log>

		<Log ID = "220120GG00073">
			<LogTime>"Jan 20 2022  1:27AM"</LogTime>
			<LogType>"FOG-Foggy Conditions"</LogType>
			<Location>"I880 N / I880 N Sr92 Con"</Location>
			<LocationDesc>"880 BTWN 92 and INDUSTRIAL"</LocationDesc>
			<Area>"Hayward"</Area>
			<ThomasBrothers>""</ThomasBrothers>
			<LATLON>"37640254:122090462"</LATLON>
			<LogDetails>
		<details>
			<DetailTime>"Jan 20 2022  2:06AM"</DetailTime>
			<IncidentDetail>"[5]  ENTER IN MEDIA LOG"</IncidentDetail>
		</details>
		<details>
			<DetailTime>"Jan 20 2022  2:06AM"</DetailTime>
			<IncidentDetail>"[4] 25-73 FOG ADVISORY FOR: 880 FRM A ST -THORNTON // and 92 TO TP // VARYING VISIBILITY FRM 150-300 FT"</IncidentDetail>
		</details>
		<details>
			<DetailTime>"Jan 20 2022  1:28AM"</DetailTime>
			<IncidentDetail>"[3]  1039 DOTCC"</IncidentDetail>
		</details>
		<details>
			<DetailTime>"Jan 20 2022  1:27AM"</DetailTime>
			<IncidentDetail>"[1] REQ FOG ADVISORY"</IncidentDetail>
		</details></LogDetails></Log>

		<Log ID = "220120GG00021">
			<LogTime>"Jan 20 2022 12:14AM"</LogTime>
			<LogType>"FOG-Foggy Conditions"</LogType>
			<Location>"3601 Telegraph Ave"</Location>
			<LocationDesc>"580 80 880 ALL OAKLAND AREA"</LocationDesc>
			<Area>"Oakland"</Area>
			<ThomasBrothers>""</ThomasBrothers>
			<LATLON>"37824339:122265682"</LATLON>
			<LogDetails>
		<details>
			<DetailTime>"Jan 20 2022 12:15AM"</DetailTime>
			<IncidentDetail>"[4]  1039 DOTCC"</IncidentDetail>
		</details>
		<details>
			<DetailTime>"Jan 20 2022 12:14AM"</DetailTime>
			<IncidentDetail>"[1] 96-55 REQ FOG ADV ALL OVER OAKLAND CHP AREA"</IncidentDetail>
		</details><units>
			<UnitTime>"Jan 20 2022 12:16AM"</UnitTime>
			<UnitDetail>"Unit At Scene"</UnitDetail></units><units>
			<UnitTime>"Jan 20 2022 12:16AM"</UnitTime>
			<UnitDetail>"Unit Enroute"</UnitDetail></units><units>
			<UnitTime>"Jan 20 2022 12:16AM"</UnitTime>
			<UnitDetail>"Unit Assigned"</UnitDetail></units></LogDetails></Log>

		<Log ID = "220120GG00001">
			<LogTime>"Jan 20 2022 12:00AM"</LogTime>
			<LogType>"TADV-Traffic Advisory"</LogType>
			<Location>"Media"</Location>
			<LocationDesc>"MEDIA"</LocationDesc>
			<Area>""</Area>
			<ThomasBrothers>""</ThomasBrothers>
			<LATLON>"0:0"</LATLON>
			<LogDetails>
		<details>
			<DetailTime>"Jan 20 2022  1:30AM"</DetailTime>
			<IncidentDetail>"[4] ***^^^FOG ADVSRY IN THE AREA OF 880 AND 92 LOG 73****^^"</IncidentDetail>
		</details>
		<details>
			<DetailTime>"Jan 20 2022 12:16AM"</DetailTime>
			<IncidentDetail>"[3] ***^^^^FOG ADVSRY IN THE AREA OF 80/580/880 IN OAKLAND LOG 21***^^^"</IncidentDetail>
		</details>
		<details>
			<DetailTime>"Jan 20 2022 12:05AM"</DetailTime>
			<IncidentDetail>"[2] ^***ISSUE FOG ADVISORY*** DENSE FOG ON I-80 AT THE BAY BRIDGE"</IncidentDetail>
		</details>
		<details>
			<DetailTime>"Jan 20 2022 12:03AM"</DetailTime>
			<IncidentDetail>"[1] ^***ISSUE FOG ADVISORY*** DENSE FOG ON US 101 AT THE GOLDEN GATE BRIDGE"</IncidentDetail>
		</details><units>
			<UnitTime>"Jan 20 2022 12:08AM"</UnitTime>
			<UnitDetail>"Unit At Scene"</UnitDetail></units><units>
			<UnitTime>"Jan 20 2022 12:08AM"</UnitTime>
			<UnitDetail>"Unit Enroute"</UnitDetail></units><units>
			<UnitTime>"Jan 20 2022 12:00AM"</UnitTime>
			<UnitDetail>"Unit Assigned"</UnitDetail></units></LogDetails></Log>

		<Log ID = "220119GG02350">
			<LogTime>"Jan 19 2022 11:21PM"</LogTime>
			<LogType>"FOG-Foggy Conditions"</LogType>
			<Location>"Sfobb Bay Bridge"</Location>
			<LocationDesc>""</LocationDesc>
			<Area>""</Area>
			<ThomasBrothers>""</ThomasBrothers>
			<LATLON>"0:0"</LATLON>
			<LogDetails>
		<details>
			<DetailTime>"Jan 19 2022 11:22PM"</DetailTime>
			<IncidentDetail>"[2]  1039 DOTCC"</IncidentDetail>
		</details>
		<details>
			<DetailTime>"Jan 19 2022 11:21PM"</DetailTime>
			<IncidentDetail>"[1] C32-081  START FOG ADVISORY"</IncidentDetail>
		</details><units>
			<UnitTime>"Jan 20 2022 12:53AM"</UnitTime>
			<UnitDetail>"Unit At Scene"</UnitDetail></units><units>
			<UnitTime>"Jan 19 2022 11:21PM"</UnitTime>
			<UnitDetail>"Unit Assigned"</UnitDetail></units><units>
			<UnitTime>"Jan 19 2022 11:21PM"</UnitTime>
			<UnitDetail>"Unit Cleared"</UnitDetail></units><units>
			<UnitTime>"Jan 19 2022 11:21PM"</UnitTime>
			<UnitDetail>"Unit At Scene"</UnitDetail></units><units>
			<UnitTime>"Jan 19 2022 11:21PM"</UnitTime>
			<UnitDetail>"Unit Enroute"</UnitDetail></units><units>
			<UnitTime>"Jan 19 2022 11:21PM"</UnitTime>
			<UnitDetail>"Unit Assigned"</UnitDetail></units></LogDetails></Log>

		<Log ID = "220119GG02164">
			<LogTime>"Jan 19 2022  9:08PM"</LogTime>
			<LogType>"CZP-Assist with Construction"</LogType>
			<Location>"101 Whipple Project"</Location>
			<LocationDesc>""</LocationDesc>
			<Area>""</Area>
			<ThomasBrothers>""</ThomasBrothers>
			<LATLON>"0:0"</LATLON>
			<LogDetails><details/><units>
			<UnitTime>"Jan 20 2022  4:52AM"</UnitTime>
			<UnitDetail>"Unit Cleared"</UnitDetail></units><units>
			<UnitTime>"Jan 20 2022 12:00AM"</UnitTime>
			<UnitDetail>"Unit At Scene"</UnitDetail></units><units>
			<UnitTime>"Jan 19 2022 11:39PM"</UnitTime>
			<UnitDetail>"Unit Enroute"</UnitDetail></units><units>
			<UnitTime>"Jan 19 2022 11:39PM"</UnitTime>
			<UnitDetail>"Unit Assigned"</UnitDetail></units><units>
			<UnitTime>"Jan 20 2022  4:52AM"</UnitTime>
			<UnitDetail>"Unit Cleared"</UnitDetail></units><units>
			<UnitTime>"Jan 19 2022 11:45PM"</UnitTime>
			<UnitDetail>"Unit At Scene"</UnitDetail></units><units>
			<UnitTime>"Jan 19 2022 11:45PM"</UnitTime>
			<UnitDetail>"Unit Enroute"</UnitDetail></units><units>
			<UnitTime>"Jan 19 2022 11:21PM"</UnitTime>
			<UnitDetail>"Unit Assigned"</UnitDetail></units><units>
			<UnitTime>"Jan 20 2022  3:21AM"</UnitTime>
			<UnitDetail>"Unit Cleared"</UnitDetail></units><units>
			<UnitTime>"Jan 19 2022 11:25PM"</UnitTime>
			<UnitDetail>"Unit At Scene"</UnitDetail></units><units>
			<UnitTime>"Jan 19 2022 10:46PM"</UnitTime>
			<UnitDetail>"Unit Enroute"</UnitDetail></units><units>
			<UnitTime>"Jan 19 2022 10:46PM"</UnitTime>
			<UnitDetail>"Unit Assigned"</UnitDetail></units><units>
			<UnitTime>"Jan 20 2022  4:35AM"</UnitTime>
			<UnitDetail>"Unit Cleared"</UnitDetail></units><units>
			<UnitTime>"Jan 19 2022 10:26PM"</UnitTime>
			<UnitDetail>"Unit At Scene"</UnitDetail></units><units>
			<UnitTime>"Jan 19 2022 10:26PM"</UnitTime>
			<UnitDetail>"Unit Enroute"</UnitDetail></units><units>
			<UnitTime>"Jan 19 2022 10:26PM"</UnitTime>
			<UnitDetail>"Unit Assigned"</UnitDetail></units><units>
			<UnitTime>"Jan 20 2022  3:34AM"</UnitTime>
			<UnitDetail>"Unit Cleared"</UnitDetail></units><units>
			<UnitTime>"Jan 19 2022 10:22PM"</UnitTime>
			<UnitDetail>"Unit At Scene"</UnitDetail></units><units>
			<UnitTime>"Jan 19 2022 10:22PM"</UnitTime>
			<UnitDetail>"Unit Enroute"</UnitDetail></units><units>
			<UnitTime>"Jan 19 2022 10:22PM"</UnitTime>
			<UnitDetail>"Unit Assigned"</UnitDetail></units><units>
			<UnitTime>"Jan 20 2022  1:40AM"</UnitTime>
			<UnitDetail>"Unit Cleared"</UnitDetail></units><units>
			<UnitTime>"Jan 19 2022 10:21PM"</UnitTime>
			<UnitDetail>"Unit At Scene"</UnitDetail></units><units>
			<UnitTime>"Jan 19 2022 10:21PM"</UnitTime>
			<UnitDetail>"Unit Enroute"</UnitDetail></units><units>
			<UnitTime>"Jan 19 2022 10:21PM"</UnitTime>
			<UnitDetail>"Unit Assigned"</UnitDetail></units><units>
			<UnitTime>"Jan 20 2022  3:29AM"</UnitTime>
			<UnitDetail>"Unit Cleared"</UnitDetail></units><units>
			<UnitTime>"Jan 19 2022 10:03PM"</UnitTime>
			<UnitDetail>"Unit At Scene"</UnitDetail></units><units>
			<UnitTime>"Jan 19 2022 10:03PM"</UnitTime>
			<UnitDetail>"Unit Enroute"</UnitDetail></units><units>
			<UnitTime>"Jan 19 2022 10:03PM"</UnitTime>
			<UnitDetail>"Unit Assigned"</UnitDetail></units><units>
			<UnitTime>"Jan 19 2022  9:55PM"</UnitTime>
			<UnitDetail>"Unit At Scene"</UnitDetail></units><units>
			<UnitTime>"Jan 19 2022  9:48PM"</UnitTime>
			<UnitDetail>"Unit Enroute"</UnitDetail></units><units>
			<UnitTime>"Jan 19 2022  9:48PM"</UnitTime>
			<UnitDetail>"Unit Assigned"</UnitDetail></units><units>
			<UnitTime>"Jan 19 2022  9:08PM"</UnitTime>
			<UnitDetail>"Unit At Scene"</UnitDetail></units><units>
			<UnitTime>"Jan 19 2022  9:08PM"</UnitTime>
			<UnitDetail>"Unit Enroute"</UnitDetail></units><units>
			<UnitTime>"Jan 19 2022  9:08PM"</UnitTime>
			<UnitDetail>"Unit Assigned"</UnitDetail></units></LogDetails></Log>

		<Log ID = "220119GG01967">
			<LogTime>"Jan 19 2022  7:39PM"</LogTime>
			<LogType>"CZP-Assist with Construction"</LogType>
			<Location>"110 Ricker : Ct Building"</Location>
			<LocationDesc>""</LocationDesc>
			<Area>""</Area>
			<ThomasBrothers>""</ThomasBrothers>
			<LATLON>"0:0"</LATLON>
			<LogDetails>
		<details>
			<DetailTime>"Jan 19 2022  7:39PM"</DetailTime>
			<IncidentDetail>"[2] 32-P15 and P16 SAME VEH"</IncidentDetail>
		</details><units>
			<UnitTime>"Jan 20 2022  4:08AM"</UnitTime>
			<UnitDetail>"Unit At Scene"</UnitDetail></units><units>
			<UnitTime>"Jan 20 2022  4:08AM"</UnitTime>
			<UnitDetail>"Unit Enroute"</UnitDetail></units><units>
			<UnitTime>"Jan 20 2022  4:08AM"</UnitTime>
			<UnitDetail>"Unit Assigned"</UnitDetail></units><units>
			<UnitTime>"Jan 20 2022  4:08AM"</UnitTime>
			<UnitDetail>"Unit At Scene"</UnitDetail></units><units>
			<UnitTime>"Jan 20 2022  4:08AM"</UnitTime>
			<UnitDetail>"Unit Assigned"</UnitDetail></units><units>
			<UnitTime>"Jan 20 2022  3:50AM"</UnitTime>
			<UnitDetail>"Unit Cleared"</UnitDetail></units><units>
			<UnitTime>"Jan 19 2022  9:55PM"</UnitTime>
			<UnitDetail>"Unit At Scene"</UnitDetail></units><units>
			<UnitTime>"Jan 19 2022  7:43PM"</UnitTime>
			<UnitDetail>"Unit Enroute"</UnitDetail></units><units>
			<UnitTime>"Jan 19 2022  7:43PM"</UnitTime>
			<UnitDetail>"Unit Assigned"</UnitDetail></units><units>
			<UnitTime>"Jan 20 2022  3:45AM"</UnitTime>
			<UnitDetail>"Unit Cleared"</UnitDetail></units><units>
			<UnitTime>"Jan 19 2022  7:39PM"</UnitTime>
			<UnitDetail>"Unit At Scene"</UnitDetail></units><units>
			<UnitTime>"Jan 19 2022  7:39PM"</UnitTime>
			<UnitDetail>"Unit Enroute"</UnitDetail></units><units>
			<UnitTime>"Jan 19 2022  7:39PM"</UnitTime>
			<UnitDetail>"Unit Assigned"</UnitDetail></units></LogDetails></Log>

		<Log ID = "220119GG01803">
			<LogTime>"Jan 19 2022  6:07PM"</LogTime>
			<LogType>"CZP-Assist with Construction"</LogType>
			<Location>"Solano"</Location>
			<LocationDesc>"*** RICHMOND SAN RAFAEL BRIDGE***"</LocationDesc>
			<Area>""</Area>
			<ThomasBrothers>""</ThomasBrothers>
			<LATLON>"0:0"</LATLON>
			<LogDetails>
		<details>
			<DetailTime>"Jan 19 2022  6:07PM"</DetailTime>
			<IncidentDetail>"[1] 18662 1283942 VEH BM 149440 IN MARIN CO RICHMOND SRFL BRIDGE TIL O500"</IncidentDetail>
		</details><units>
			<UnitTime>"Jan 19 2022  6:07PM"</UnitTime>
			<UnitDetail>"Unit At Scene"</UnitDetail></units><units>
			<UnitTime>"Jan 19 2022  6:07PM"</UnitTime>
			<UnitDetail>"Unit Enroute"</UnitDetail></units><units>
			<UnitTime>"Jan 19 2022  6:07PM"</UnitTime>
			<UnitDetail>"Unit Assigned"</UnitDetail></units></LogDetails></Log>

		<Log ID = "220119GG00297">
			<LogTime>"Jan 19 2022  6:37AM"</LogTime>
			<LogType>"CLOSURE of a Road"</LogType>
			<Location>"0 Us101 S"</Location>
			<LocationDesc>"NB 101/OLOMPALI-SAN ANTONIO, #2"</LocationDesc>
			<Area>"Marin"</Area>
			<ThomasBrothers>""</ThomasBrothers>
			<LATLON>"38150829:122567295"</LATLON>
			<LogDetails>
		<details>
			<DetailTime>"Jan 19 2022  6:53AM"</DetailTime>
			<IncidentDetail>"[7] 34-801  #2"</IncidentDetail>
		</details>
		<details>
			<DetailTime>"Jan 19 2022  6:39AM"</DetailTime>
			<IncidentDetail>"[2] #2 // EMERG TREE REMOVAL"</IncidentDetail>
		</details><units>
			<UnitTime>"Jan 19 2022  6:52AM"</UnitTime>
			<UnitDetail>"Unit At Scene"</UnitDetail></units><units>
			<UnitTime>"Jan 19 2022  6:52AM"</UnitTime>
			<UnitDetail>"Unit Enroute"</UnitDetail></units><units>
			<UnitTime>"Jan 19 2022  6:52AM"</UnitTime>
			<UnitDetail>"Unit Assigned"</UnitDetail></units></LogDetails></Log>
</Dispatch>
<Dispatch ID = "VTCC">

		<Log ID = "220120VT00016">
			<LogTime>"Jan 20 2022  2:49AM"</LogTime>
			<LogType>"1179-Trfc Collision-1141 Enrt"</LogType>
			<Location>"Us101 S / Lynn Rd"</Location>
			<LocationDesc>"JNO"</LocationDesc>
			<Area>"Moorpark"</Area>
			<ThomasBrothers>""</ThomasBrothers>
			<LATLON>"34183333:118891389"</LATLON>
			<LogDetails>
		<details>
			<DetailTime>"Jan 20 2022  4:53AM"</DetailTime>
			<IncidentDetail>"[22] [Rotation Request Comment] 1039 ROYS 805-498-6325"</IncidentDetail>
		</details>
		<details>
			<DetailTime>"Jan 20 2022  4:51AM"</DetailTime>
			<IncidentDetail>"[21] 31-S5   START 1185 HEAVY DUTY  // WILL NEED ROTATOR AND FORK LIFTS TO OFF LOAD THE TRAILER //23,000 LBS"</IncidentDetail>
		</details>
		<details>
			<DetailTime>"Jan 20 2022  3:44AM"</DetailTime>
			<IncidentDetail>"[14] [Notification] [CHP]-45-1 HR ETA FOR CT'S [Shared]"</IncidentDetail>
		</details>
		<details>
			<DetailTime>"Jan 20 2022  3:39AM"</DetailTime>
			<IncidentDetail>"[13] 31-S5  START CALTRANS SUPERVISOR // 1039 CALTRANS"</IncidentDetail>
		</details>
		<details>
			<DetailTime>"Jan 20 2022  3:38AM"</DetailTime>
			<IncidentDetail>"[12] C54-070  START CALTRANS FOR HARD CLOSURE"</IncidentDetail>
		</details>
		<details>
			<DetailTime>"Jan 20 2022  3:31AM"</DetailTime>
			<IncidentDetail>"[11] 31-S5    #3-4 LANES CLOSED"</IncidentDetail>
		</details>
		<details>
			<DetailTime>"Jan 20 2022  3:07AM"</DetailTime>
			<IncidentDetail>"[7] [Notification] [CHP]-Problem changed from 1183-Trfc Collision-Unkn Inj to 1179-Trfc Collision-1141 Enrt [Shared]"</IncidentDetail>
		</details>
		<details>
			<DetailTime>"Jan 20 2022  3:07AM"</DetailTime>
			<IncidentDetail>"[6] 1039 VCFD"</IncidentDetail>
		</details>
		<details>
			<DetailTime>"Jan 20 2022  3:07AM"</DetailTime>
			<IncidentDetail>"[5] C54-070   START FULL RESPONSE //PRTY TRAPPED  IN O/TURNED BIG RIG"</IncidentDetail>
		</details>
		<details>
			<DetailTime>"Jan 20 2022  3:05AM"</DetailTime>
			<IncidentDetail>"[4] C54-070  START  1141  FOR PRECAUTIONARY   / 1039 VCFD"</IncidentDetail>
		</details>
		<details>
			<DetailTime>"Jan 20 2022  2:50AM"</DetailTime>
			<IncidentDetail>"[2] EVERYTHING ON RS"</IncidentDetail>
		</details>
		<details>
			<DetailTime>"Jan 20 2022  2:50AM"</DetailTime>
			<IncidentDetail>"[1] SEMI TRUCK OR BOX TRUCK VS SIGN"</IncidentDetail>
		</details><units>
			<UnitTime>"Jan 20 2022  5:25AM"</UnitTime>
			<UnitDetail>"Unit Assigned"</UnitDetail></units><units>
			<UnitTime>"Jan 20 2022  4:41AM"</UnitTime>
			<UnitDetail>"Unit At Scene"</UnitDetail></units><units>
			<UnitTime>"Jan 20 2022  4:22AM"</UnitTime>
			<UnitDetail>"Unit Enroute"</UnitDetail></units><units>
			<UnitTime>"Jan 20 2022  4:22AM"</UnitTime>
			<UnitDetail>"Unit Assigned"</UnitDetail></units><units>
			<UnitTime>"Jan 20 2022  5:20AM"</UnitTime>
			<UnitDetail>"Unit Cleared"</UnitDetail></units><units>
			<UnitTime>"Jan 20 2022  3:31AM"</UnitTime>
			<UnitDetail>"Unit At Scene"</UnitDetail></units><units>
			<UnitTime>"Jan 20 2022  3:15AM"</UnitTime>
			<UnitDetail>"Unit Enroute"</UnitDetail></units><units>
			<UnitTime>"Jan 20 2022  3:15AM"</UnitTime>
			<UnitDetail>"Unit Assigned"</UnitDetail></units><units>
			<UnitTime>"Jan 20 2022  4:02AM"</UnitTime>
			<UnitDetail>"Unit Cleared"</UnitDetail></units><units>
			<UnitTime>"Jan 20 2022  3:20AM"</UnitTime>
			<UnitDetail>"Unit At Scene"</UnitDetail></units><units>
			<UnitTime>"Jan 20 2022  3:13AM"</UnitTime>
			<UnitDetail>"Unit Enroute"</UnitDetail></units><units>
			<UnitTime>"Jan 20 2022  3:13AM"</UnitTime>
			<UnitDetail>"Unit Assigned"</UnitDetail></units><units>
			<UnitTime>"Jan 20 2022  4:55AM"</UnitTime>
			<UnitDetail>"Unit Cleared"</UnitDetail></units><units>
			<UnitTime>"Jan 20 2022  3:27AM"</UnitTime>
			<UnitDetail>"Unit At Scene"</UnitDetail></units><units>
			<UnitTime>"Jan 20 2022  3:11AM"</UnitTime>
			<UnitDetail>"Unit Enroute"</UnitDetail></units><units>
			<UnitTime>"Jan 20 2022  3:11AM"</UnitTime>
			<UnitDetail>"Unit Assigned"</UnitDetail></units><units>
			<UnitTime>"Jan 20 2022  3:05AM"</UnitTime>
			<UnitDetail>"Unit At Scene"</UnitDetail></units><units>
			<UnitTime>"Jan 20 2022  3:05AM"</UnitTime>
			<UnitDetail>"Unit Enroute"</UnitDetail></units><units>
			<UnitTime>"Jan 20 2022  2:51AM"</UnitTime>
			<UnitDetail>"Unit Assigned"</UnitDetail></units></LogDetails></Log>

		<Log ID = "220120VT00009">
			<LogTime>"Jan 20 2022  1:38AM"</LogTime>
			<LogType>"1182-Trfc Collision-No Inj"</LogType>
			<Location>"Tico Rd / W Lomita Ave"</Location>
			<LocationDesc>""</LocationDesc>
			<Area>"Ventura"</Area>
			<ThomasBrothers>""</ThomasBrothers>
			<LATLON>"34443462:119281746"</LATLON>
			<LogDetails>
		<details>
			<DetailTime>"Jan 20 2022  3:25AM"</DetailTime>
			<IncidentDetail>"[15] [Notification] [CHP]-Problem changed from 1183-Trfc Collision-Unkn Inj to 1182-Trfc Collision-No Inj by CHP"</IncidentDetail>
		</details>
		<details>
			<DetailTime>"Jan 20 2022  2:17AM"</DetailTime>
			<IncidentDetail>"[4] [Rotation Request Comment] 1039 ADAMSON 805-646-1945"</IncidentDetail>
		</details>
		<details>
			<DetailTime>"Jan 20 2022  2:17AM"</DetailTime>
			<IncidentDetail>"[3] C31-012   1015  22408  1185 FOR BLK HARLEY"</IncidentDetail>
		</details><units>
			<UnitTime>"Jan 20 2022  2:15AM"</UnitTime>
			<UnitDetail>"Unit At Scene"</UnitDetail></units><units>
			<UnitTime>"Jan 20 2022  2:09AM"</UnitTime>
			<UnitDetail>"Unit Enroute"</UnitDetail></units><units>
			<UnitTime>"Jan 20 2022  1:39AM"</UnitTime>
			<UnitDetail>"Unit Assigned"</UnitDetail></units></LogDetails></Log>

		<Log ID = "220119VT00309">
			<LogTime>"Jan 19 2022 11:41PM"</LogTime>
			<LogType>"20002-Hit and Run No Injuries"</LogType>
			<Location>"390 Old Mill Rd"</Location>
			<LocationDesc>""</LocationDesc>
			<Area>"Santa Barbara"</Area>
			<ThomasBrothers>""</ThomasBrothers>
			<LATLON>"34443917:119764517"</LATLON>
			<LogDetails>
		<details>
			<DetailTime>"Jan 20 2022  3:12AM"</DetailTime>
			<IncidentDetail>"[57] 1039 SBSO"</IncidentDetail>
		</details>
		<details>
			<DetailTime>"Jan 20 2022  1:09AM"</DetailTime>
			<IncidentDetail>"[53] 1039 CT"</IncidentDetail>
		</details>
		<details>
			<DetailTime>"Jan 20 2022  1:09AM"</DetailTime>
			<IncidentDetail>"[52] 401 EL SUENO OFR DELINEATOR AND ATTENUATOR HAS DMG - REG ROUNDS"</IncidentDetail>
		</details>
		<details>
			<DetailTime>"Jan 20 2022  1:01AM"</DetailTime>
			<IncidentDetail>"[49] [Rotation Request Comment] 1039 805 ROADSIDE 805 708 3318"</IncidentDetail>
		</details>
		<details>
			<DetailTime>"Jan 20 2022  1:00AM"</DetailTime>
			<IncidentDetail>"[48] 1039 SBSO 1022 THOMAS"</IncidentDetail>
		</details>
		<details>
			<DetailTime>"Jan 20 2022 12:52AM"</DetailTime>
			<IncidentDetail>"[46] [Notification] [CHP]-PER SBSO  THEY STARTED THOMAS TOW  [Shared]"</IncidentDetail>
		</details>
		<details>
			<DetailTime>"Jan 20 2022 12:14AM"</DetailTime>
			<IncidentDetail>"[39] 1039 SBSO FOR 1141"</IncidentDetail>
		</details>
		<details>
			<DetailTime>"Jan 19 2022 11:53PM"</DetailTime>
			<IncidentDetail>"[30] 1039 SBPD"</IncidentDetail>
		</details>
		<details>
			<DetailTime>"Jan 19 2022 11:51PM"</DetailTime>
			<IncidentDetail>"[27] 1039 SBSO"</IncidentDetail>
		</details>
		<details>
			<DetailTime>"Jan 19 2022 11:49PM"</DetailTime>
			<IncidentDetail>"[22] PER ADDILT DEBRIS ON OFR"</IncidentDetail>
		</details>
		<details>
			<DetailTime>"Jan 19 2022 11:48PM"</DetailTime>
			<IncidentDetail>"[20] VEH IS SMOKING W/ FRONT END DAMAGE // DRIVER APPEARS HBD"</IncidentDetail>
		</details>
		<details>
			<DetailTime>"Jan 19 2022 11:48PM"</DetailTime>
			<IncidentDetail>"[18] [Notification] [CHP]-VEH NOW PARKED AT 340 OLD MILL RD // DRIVER WALKING AWAY TOWARDS CALLE REAL [Shared]"</IncidentDetail>
		</details>
		<details>
			<DetailTime>"Jan 19 2022 11:46PM"</DetailTime>
			<IncidentDetail>"[14] WHI PK TRUCK  W/ FRONT END DAMAGE    // NOW AT THE END OF OLD MILL  RD   OUTSIDE MOBILE HOME PARK"</IncidentDetail>
		</details>
		<details>
			<DetailTime>"Jan 19 2022 11:44PM"</DetailTime>
			<IncidentDetail>"[10] [Appended, 23:45:41] [3] VEH AT HIGH SPEEDS AND BURNOUTS"</IncidentDetail>
		</details>
		<details>
			<DetailTime>"Jan 19 2022 11:44PM"</DetailTime>
			<IncidentDetail>"[7] 10398 SBPD TO BOL FOR VEH"</IncidentDetail>
		</details>
		<details>
			<DetailTime>"Jan 19 2022 11:43PM"</DetailTime>
			<IncidentDetail>"[6] DAMAGE TO KRAIL ON OFR"</IncidentDetail>
		</details>
		<details>
			<DetailTime>"Jan 19 2022 11:43PM"</DetailTime>
			<IncidentDetail>"[5] VEH EXITED EL SUENO AND HEADED TOWARDS UPPER STATE"</IncidentDetail>
		</details>
		<details>
			<DetailTime>"Jan 19 2022 11:42PM"</DetailTime>
			<IncidentDetail>"[3] FRNT BUMPER DAMAGE AND TIRE SIDEWAYS ON VEH"</IncidentDetail>
		</details>
		<details>
			<DetailTime>"Jan 19 2022 11:42PM"</DetailTime>
			<IncidentDetail>"[2] TC'ED ON THE OFR - HIT KRAIL"</IncidentDetail>
		</details><units>
			<UnitTime>"Jan 20 2022 12:43AM"</UnitTime>
			<UnitDetail>"Unit At Scene"</UnitDetail></units><units>
			<UnitTime>"Jan 20 2022 12:41AM"</UnitTime>
			<UnitDetail>"Unit Enroute"</UnitDetail></units><units>
			<UnitTime>"Jan 19 2022 11:45PM"</UnitTime>
			<UnitDetail>"Unit Assigned"</UnitDetail></units></LogDetails></Log>

		<Log ID = "220119VT00306">
			<LogTime>"Jan 19 2022 11:29PM"</LogTime>
			<LogType>"CZP-Assist with Construction"</LogType>
			<Location>"610 Spring Rd"</Location>
			<LocationDesc>"=========ALTADENA ============"</LocationDesc>
			<Area>"VT"</Area>
			<ThomasBrothers>""</ThomasBrothers>
			<LATLON>"34282974:118874632"</LATLON>
			<LogDetails>
		<details>
			<DetailTime>"Jan 19 2022 11:30PM"</DetailTime>
			<IncidentDetail>"[1] 137-027  ID 15498 VEH 1453480 BM 200125"</IncidentDetail>
		</details><units>
			<UnitTime>"Jan 19 2022 11:30PM"</UnitTime>
			<UnitDetail>"Unit At Scene"</UnitDetail></units><units>
			<UnitTime>"Jan 19 2022 11:29PM"</UnitTime>
			<UnitDetail>"Unit Assigned"</UnitDetail></units></LogDetails></Log>
</Dispatch>
<Dispatch ID = "SLCC">

		<Log ID = "220120SL00011">
			<LogTime>"Jan 20 2022  2:12AM"</LogTime>
			<LogType>"SIG Alert"</LogType>
			<Location>"Avila Beach Dr / San Luis Bay Dr"</Location>
			<LocationDesc>""</LocationDesc>
			<Area>"San Luis Obispo"</Area>
			<ThomasBrothers>""</ThomasBrothers>
			<LATLON>"35187854:120719020"</LATLON>
			<LogDetails>
		<details>
			<DetailTime>"Jan 20 2022  4:40AM"</DetailTime>
			<IncidentDetail>"[9] 1039 JOSH W CO RDS [Shared]"</IncidentDetail>
		</details>
		<details>
			<DetailTime>"Jan 20 2022  4:39AM"</DetailTime>
			<IncidentDetail>"[8] CALFIRE ADVS RDWY CAN BE OPENED NOW [Shared]"</IncidentDetail>
		</details>
		<details>
			<DetailTime>"Jan 20 2022  2:14AM"</DetailTime>
			<IncidentDetail>"[7] [CHP] has closed their incident [220120SL00004]"</IncidentDetail>
		</details>
		<details>
			<DetailTime>"Jan 20 2022  2:13AM"</DetailTime>
			<IncidentDetail>"[5] ROAD WILL BE CLOSED FOR UNK DURATION"</IncidentDetail>
		</details>
		<details>
			<DetailTime>"Jan 20 2022  2:13AM"</DetailTime>
			<IncidentDetail>"[4] ISSUE SIGALERT"</IncidentDetail>
		</details>
		<details>
			<DetailTime>"Jan 20 2022  2:12AM"</DetailTime>
			<IncidentDetail>"[1] AVILA BEACH DR CLOSED FROM SAN LUIS BAY DR TO ONTARIO RD"</IncidentDetail>
		</details></LogDetails></Log>
</Dispatch>
</Center>

<Center ID = "LAHB">
<Dispatch ID = "LACC">

		<Log ID = "220120LA00394">
			<LogTime>"Jan 20 2022  5:18AM"</LogTime>
			<LogType>"1125-Traffic Hazard"</LogType>
			<Location>"17601 Lone Pine Trl"</Location>
			<LocationDesc>""</LocationDesc>
			<Area>"Antelope Valley"</Area>
			<ThomasBrothers>""</ThomasBrothers>
			<LATLON>"34676231:118441230"</LATLON>
			<LogDetails>
		<details>
			<DetailTime>"Jan 20 2022  5:22AM"</DetailTime>
			<IncidentDetail>"[1] RP ADV A GREEN VAN IS PARKED IN THE RDWY IN A WAY THAT  IS BLOCKING THE STREET -RP ADV EMERGENCY VEHS WOULD NOT BE ABLE TO GET THROUGH -"</IncidentDetail>
		</details></LogDetails></Log>

		<Log ID = "220120LA00391">
			<LogTime>"Jan 20 2022  5:13AM"</LogTime>
			<LogType>"FIRE-Report of Fire"</LogType>
			<Location>"I210 E / S Myrtle Ave"</Location>
			<LocationDesc>"EVERGREEN AT MAYFLOWER"</LocationDesc>
			<Area>"Baldwin Park"</Area>
			<ThomasBrothers>""</ThomasBrothers>
			<LATLON>"34135357:118000743"</LATLON>
			<LogDetails>
		<details>
			<DetailTime>"Jan 20 2022  5:15AM"</DetailTime>
			<IncidentDetail>"[3] POSS HOMELESS ENCAMPMENT FIRE"</IncidentDetail>
		</details>
		<details>
			<DetailTime>"Jan 20 2022  5:15AM"</DetailTime>
			<IncidentDetail>"[2] FIRE IS ADJ TO THE FWY POSS NEAR EVERGREEN AT MAYFLOWER TOWARD THE EMBANKMENT OF THE 210 FWY 1039 FD"</IncidentDetail>
		</details></LogDetails></Log>

		<Log ID = "220120LA00387">
			<LogTime>"Jan 20 2022  5:05AM"</LogTime>
			<LogType>"1182-Trfc Collision-No Inj"</LogType>
			<Location>"I110 N / James M Wood Blvd"</Location>
			<LocationDesc>"JAMES M WOOD ONR TO NB 110"</LocationDesc>
			<Area>"Central LA"</Area>
			<ThomasBrothers>""</ThomasBrothers>
			<LATLON>"34047822:118266564"</LATLON>
			<LogDetails>
		<details>
			<DetailTime>"Jan 20 2022  5:14AM"</DetailTime>
			<IncidentDetail>"[5] 1039 METRO TOWING INC-323-342-0602 - ETA 15MINS"</IncidentDetail>
		</details>
		<details>
			<DetailTime>"Jan 20 2022  5:11AM"</DetailTime>
			<IncidentDetail>"[3] 15-50 REQ 1185"</IncidentDetail>
		</details>
		<details>
			<DetailTime>"Jan 20 2022  5:10AM"</DetailTime>
			<IncidentDetail>"[2] WHI CARGO/FLEET VAN W/ TRLR VS RS GUARDRAIL"</IncidentDetail>
		</details>
		<details>
			<DetailTime>"Jan 20 2022  5:07AM"</DetailTime>
			<IncidentDetail>"[1] SOLO VEH TC BLKG THE SINGLE LANE ONR"</IncidentDetail>
		</details><units>
			<UnitTime>"Jan 20 2022  5:24AM"</UnitTime>
			<UnitDetail>"Unit At Scene"</UnitDetail></units><units>
			<UnitTime>"Jan 20 2022  5:11AM"</UnitTime>
			<UnitDetail>"Unit Assigned"</UnitDetail></units><units>
			<UnitTime>"Jan 20 2022  5:21AM"</UnitTime>
			<UnitDetail>"Unit At Scene"</UnitDetail></units><units>
			<UnitTime>"Jan 20 2022  5:11AM"</UnitTime>
			<UnitDetail>"Unit Assigned"</UnitDetail></units></LogDetails></Log>

		<Log ID = "220120LA00370">
			<LogTime>"Jan 20 2022  4:54AM"</LogTime>
			<LogType>"1125-Traffic Hazard"</LogType>
			<Location>"I405 S / CRENSHAW RD ONR"</Location>
			<LocationDesc>"SB 405 JSO CRENSHAW"</LocationDesc>
			<Area>"South LA"</Area>
			<ThomasBrothers>""</ThomasBrothers>
			<LATLON>"33864502:118326624"</LATLON>
			<LogDetails>
		<details>
			<DetailTime>"Jan 20 2022  5:24AM"</DetailTime>
			<IncidentDetail>"[33] PTY IS 1023 FOR PRVT ASST AND REQ CHP TO STANDBY UNTIL THEY GO ON SCENE -- ETA 30 --"</IncidentDetail>
		</details>
		<details>
			<DetailTime>"Jan 20 2022  5:10AM"</DetailTime>
			<IncidentDetail>"[32] 1039 FALCON TOW COPIES 1022 AND BOT"</IncidentDetail>
		</details>
		<details>
			<DetailTime>"Jan 20 2022  5:10AM"</DetailTime>
			<IncidentDetail>"[31] 77-400 1022 1185"</IncidentDetail>
		</details>
		<details>
			<DetailTime>"Jan 20 2022  5:09AM"</DetailTime>
			<IncidentDetail>"[30] 77-400 ALL VEHS OFF AT WESTERN"</IncidentDetail>
		</details>
		<details>
			<DetailTime>"Jan 20 2022  5:06AM"</DetailTime>
			<IncidentDetail>"[23] [Rotation Request Comment] 1039 Falcon Towing-Gardena 310-329-8910 ENRT // ETA: 20 O/LESS"</IncidentDetail>
		</details>
		<details>
			<DetailTime>"Jan 20 2022  5:05AM"</DetailTime>
			<IncidentDetail>"[27] [Appended, 05:06:57] [3] PEOPLE STANDING IN TRAFFIC LNS"</IncidentDetail>
		</details>
		<details>
			<DetailTime>"Jan 20 2022  5:04AM"</DetailTime>
			<IncidentDetail>"[25] [Appended, 05:06:57] [1] TWO VEHS IN SLO LN"</IncidentDetail>
		</details>
		<details>
			<DetailTime>"Jan 20 2022  5:04AM"</DetailTime>
			<IncidentDetail>"[15] CORR 1020 SB 405JSO ARTESIA -- PLS ROLL 1185"</IncidentDetail>
		</details>
		<details>
			<DetailTime>"Jan 20 2022  4:55AM"</DetailTime>
			<IncidentDetail>"[2] SLO LN -- NO RS IN THE AREA DUE TO CONSTRUCTION"</IncidentDetail>
		</details><units>
			<UnitTime>"Jan 20 2022  5:06AM"</UnitTime>
			<UnitDetail>"Unit At Scene"</UnitDetail></units><units>
			<UnitTime>"Jan 20 2022  4:56AM"</UnitTime>
			<UnitDetail>"Unit Assigned"</UnitDetail></units></LogDetails></Log>

		<Log ID = "220120LA00369">
			<LogTime>"Jan 20 2022  4:53AM"</LogTime>
			<LogType>"1183-Trfc Collision-Unkn Inj"</LogType>
			<Location>"Sr91 W / S Vermont Ave"</Location>
			<LocationDesc>"WB JEO"</LocationDesc>
			<Area>"South LA"</Area>
			<ThomasBrothers>""</ThomasBrothers>
			<LATLON>"33872875:118290904"</LATLON>
			<LogDetails>
		<details>
			<DetailTime>"Jan 20 2022  5:08AM"</DetailTime>
			<IncidentDetail>"[14] VAN LINGEN'S COPIES LN 11"</IncidentDetail>
		</details>
		<details>
			<DetailTime>"Jan 20 2022  5:05AM"</DetailTime>
			<IncidentDetail>"[13] PLS ADVS 1185 THAT THEY MAY NEED 2 1185S W/ CABLE -- VEH IS DOWN THE WASH -- APPROX 10 FT DOWN THE WASH"</IncidentDetail>
		</details>
		<details>
			<DetailTime>"Jan 20 2022  5:03AM"</DetailTime>
			<IncidentDetail>"[12] [Rotation Request Comment] 1039 Van Lingen's Tow 310-602-4970 ENRT // ETA: 20 O/LESS"</IncidentDetail>
		</details>
		<details>
			<DetailTime>"Jan 20 2022  5:02AM"</DetailTime>
			<IncidentDetail>"[11] [Notification] [CHP]-PER LAFD OP # 207 ----- THEY ARE 97 WB 91 ON VERMONT OFR ***** INC # 209  [Shared]"</IncidentDetail>
		</details>
		<details>
			<DetailTime>"Jan 20 2022  5:01AM"</DetailTime>
			<IncidentDetail>"[6] 77-310 PLS ROLL 1185 W/ AT LEAST 20 FT OF CABLE THANK YOU -- VEH IS 1124"</IncidentDetail>
		</details>
		<details>
			<DetailTime>"Jan 20 2022  5:01AM"</DetailTime>
			<IncidentDetail>"[7] [Appended, 05:02:03] [1] VEH OFF THE EMBANKMENT"</IncidentDetail>
		</details>
		<details>
			<DetailTime>"Jan 20 2022  4:55AM"</DetailTime>
			<IncidentDetail>"[2] [Appended, 04:56:03] [1] VEH O/ EMBANKMENT  , UNK IF ANYONE IN VEH"</IncidentDetail>
		</details>
		<details>
			<DetailTime>"Jan 20 2022  4:55AM"</DetailTime>
			<IncidentDetail>"[1] VEH POSS INTO RS EMBANKMENT // RP ADVS HE SAW LIGHTS THAT LOOKED LIKE A VEH HAD TC'D - NFI"</IncidentDetail>
		</details><units>
			<UnitTime>"Jan 20 2022  5:24AM"</UnitTime>
			<UnitDetail>"Unit At Scene"</UnitDetail></units><units>
			<UnitTime>"Jan 20 2022  4:59AM"</UnitTime>
			<UnitDetail>"Unit Enroute"</UnitDetail></units><units>
			<UnitTime>"Jan 20 2022  4:59AM"</UnitTime>
			<UnitDetail>"Unit Assigned"</UnitDetail></units><units>
			<UnitTime>"Jan 20 2022  5:01AM"</UnitTime>
			<UnitDetail>"Unit At Scene"</UnitDetail></units><units>
			<UnitTime>"Jan 20 2022  4:56AM"</UnitTime>
			<UnitDetail>"Unit Assigned"</UnitDetail></units></LogDetails></Log>

		<Log ID = "220120LA00332">
			<LogTime>"Jan 20 2022  4:24AM"</LogTime>
			<LogType>"1183-Trfc Collision-Unkn Inj"</LogType>
			<Location>"I210 W / Paxton St Ofr"</Location>
			<LocationDesc>"WB 210 JEO PAXTON"</LocationDesc>
			<Area>"Altadena"</Area>
			<ThomasBrothers>""</ThomasBrothers>
			<LATLON>"34284941:118404050"</LATLON>
			<LogDetails>
		<details>
			<DetailTime>"Jan 20 2022  4:56AM"</DetailTime>
			<IncidentDetail>"[16] RDWY CLR VEH ON THE RS"</IncidentDetail>
		</details>
		<details>
			<DetailTime>"Jan 20 2022  4:44AM"</DetailTime>
			<IncidentDetail>"[14] VAN  1124 RQ 1185"</IncidentDetail>
		</details>
		<details>
			<DetailTime>"Jan 20 2022  4:28AM"</DetailTime>
			<IncidentDetail>"[11] BIG RIG DRVR REQ CHP FOR 1110 -- TIRE CAUSED DMG TO RIG AND IS STILL STUCK UNDER HIS VEH --- SAG'D ."</IncidentDetail>
		</details>
		<details>
			<DetailTime>"Jan 20 2022  4:27AM"</DetailTime>
			<IncidentDetail>"[7] [Appended, 04:28:10] [2] WHI VAN WAS FACING W/WAY , POSS PREV TC  , RP HIT THE VAN"</IncidentDetail>
		</details>
		<details>
			<DetailTime>"Jan 20 2022  4:27AM"</DetailTime>
			<IncidentDetail>"[6] [Appended, 04:28:10] [1] 2 VEH TC ,  WHI CHEV SILV  VS  WHI VAN"</IncidentDetail>
		</details>
		<details>
			<DetailTime>"Jan 20 2022  4:27AM"</DetailTime>
			<IncidentDetail>"[4] [Appended, 04:27:46] [3] VEH BLKNG #1 LN"</IncidentDetail>
		</details>
		<details>
			<DetailTime>"Jan 20 2022  4:26AM"</DetailTime>
			<IncidentDetail>"[3] [Appended, 04:27:46] [2] LOST A WHEEL --- RP HIT THE WHEEL ----- TIRE UNDER HIS BIG RIG"</IncidentDetail>
		</details>
		<details>
			<DetailTime>"Jan 20 2022  4:26AM"</DetailTime>
			<IncidentDetail>"[1] RP WIT A CHEV SLV TC INTO A VAN THAT WAS SIDEWAYS BLKING #1 LN "</IncidentDetail>
		</details>
		<details>
			<DetailTime>"Jan 20 2022  4:26AM"</DetailTime>
			<IncidentDetail>"[2] [Appended, 04:27:46] [1] VEH VS CD WALL"</IncidentDetail>
		</details><units>
			<UnitTime>"Jan 20 2022  4:41AM"</UnitTime>
			<UnitDetail>"Unit At Scene"</UnitDetail></units><units>
			<UnitTime>"Jan 20 2022  4:27AM"</UnitTime>
			<UnitDetail>"Unit Assigned"</UnitDetail></units></LogDetails></Log>

		<Log ID = "220120LA00300">
			<LogTime>"Jan 20 2022  3:41AM"</LogTime>
			<LogType>"1179-Trfc Collision-1141 Enrt"</LogType>
			<Location>"1251 S Atlantic Blvd"</Location>
			<LocationDesc>""</LocationDesc>
			<Area>"East LA"</Area>
			<ThomasBrothers>""</ThomasBrothers>
			<LATLON>"34015073:118158902"</LATLON>
			<LogDetails>
		<details>
			<DetailTime>"Jan 20 2022  4:16AM"</DetailTime>
			<IncidentDetail>"[17] [Rotation Request Comment] 1039 PEPE'S TOW 323-264-1733 ENRT ETA 15-20"</IncidentDetail>
		</details>
		<details>
			<DetailTime>"Jan 20 2022  4:14AM"</DetailTime>
			<IncidentDetail>"[16] C82-600  REQ 1185"</IncidentDetail>
		</details>
		<details>
			<DetailTime>"Jan 20 2022  4:04AM"</DetailTime>
			<IncidentDetail>"[14] [Notification] [CHP]-PTY LN / ROBINSON CLR JDIC"</IncidentDetail>
		</details>
		<details>
			<DetailTime>"Jan 20 2022  3:45AM"</DetailTime>
			<IncidentDetail>"[4] 1039 LACO FD"</IncidentDetail>
		</details>
		<details>
			<DetailTime>"Jan 20 2022  3:44AM"</DetailTime>
			<IncidentDetail>"[2] 2 VEH TC POSS INJ // VV IS A FORD RANGER ADDTL HONDA CIVIC HAS A MALE INSIDE NON RESPONSIVE"</IncidentDetail>
		</details>
		<details>
			<DetailTime>"Jan 20 2022  3:42AM"</DetailTime>
			<IncidentDetail>"[1] SPANISH TRANS ID 338717"</IncidentDetail>
		</details><units>
			<UnitTime>"Jan 20 2022  4:36AM"</UnitTime>
			<UnitDetail>"Unit Cleared"</UnitDetail></units><units>
			<UnitTime>"Jan 20 2022  3:51AM"</UnitTime>
			<UnitDetail>"Unit At Scene"</UnitDetail></units><units>
			<UnitTime>"Jan 20 2022  3:50AM"</UnitTime>
			<UnitDetail>"Unit Enroute"</UnitDetail></units><units>
			<UnitTime>"Jan 20 2022  3:50AM"</UnitTime>
			<UnitDetail>"Unit Assigned"</UnitDetail></units><units>
			<UnitTime>"Jan 20 2022  3:50AM"</UnitTime>
			<UnitDetail>"Unit At Scene"</UnitDetail></units><units>
			<UnitTime>"Jan 20 2022  3:47AM"</UnitTime>
			<UnitDetail>"Unit Enroute"</UnitDetail></units><units>
			<UnitTime>"Jan 20 2022  3:47AM"</UnitTime>
			<UnitDetail>"Unit Assigned"</UnitDetail></units></LogDetails></Log>

		<Log ID = "220120LA00007">
			<LogTime>"Jan 20 2022 12:01AM"</LogTime>
			<LogType>"1013-Road/Weather Conditions"</LogType>
			<Location>"2901 W Broadway"</Location>
			<LocationDesc>"LACO ROAD/WEATHER LOG"</LocationDesc>
			<Area>"LA"</Area>
			<ThomasBrothers>""</ThomasBrothers>
			<LATLON>"34144921:118227297"</LATLON>
			<LogDetails><details/><units>
			<UnitTime>"Jan 20 2022 12:02AM"</UnitTime>
			<UnitDetail>"Unit At Scene"</UnitDetail></units><units>
			<UnitTime>"Jan 20 2022 12:02AM"</UnitTime>
			<UnitDetail>"Unit Enroute"</UnitDetail></units><units>
			<UnitTime>"Jan 20 2022 12:02AM"</UnitTime>
			<UnitDetail>"Unit Assigned"</UnitDetail></units></LogDetails></Log>

		<Log ID = "220120LA00001">
			<LogTime>"Jan 19 2022 11:59PM"</LogTime>
			<LogType>"1013-Road/Weather Conditions"</LogType>
			<Location>"Media Log"</Location>
			<LocationDesc>"LOS ANGELES COUNTY"</LocationDesc>
			<Area>"LA"</Area>
			<ThomasBrothers>""</ThomasBrothers>
			<LATLON>"34144921:118227297"</LATLON>
			<LogDetails>
		<details>
			<DetailTime>"Jan 20 2022 12:00AM"</DetailTime>
			<IncidentDetail>"[2] ^NO CHP SIGALERTS IN LOS ANGELES COUNTY"</IncidentDetail>
		</details>
		<details>
			<DetailTime>"Jan 20 2022 12:00AM"</DetailTime>
			<IncidentDetail>"[1] ^MEDIA LOG FOR JANUARY 20, 2022"</IncidentDetail>
		</details><units>
			<UnitTime>"Jan 20 2022 12:07AM"</UnitTime>
			<UnitDetail>"Unit At Scene"</UnitDetail></units><units>
			<UnitTime>"Jan 20 2022 12:07AM"</UnitTime>
			<UnitDetail>"Unit Assigned"</UnitDetail></units></LogDetails></Log>

		<Log ID = "220119LA03041">
			<LogTime>"Jan 19 2022  9:44PM"</LogTime>
			<LogType>"CZP-Assist with Construction"</LogType>
			<Location>"I110 S / W Manchester Ave"</Location>
			<LocationDesc>"STRAIGHT RAMP"</LocationDesc>
			<Area>"Central LA"</Area>
			<ThomasBrothers>""</ThomasBrothers>
			<LATLON>"33960128:118281097"</LATLON>
			<LogDetails><details/><units>
			<UnitTime>"Jan 20 2022  1:40AM"</UnitTime>
			<UnitDetail>"Unit At Scene"</UnitDetail></units><units>
			<UnitTime>"Jan 19 2022 10:40PM"</UnitTime>
			<UnitDetail>"Unit Assigned"</UnitDetail></units><units>
			<UnitTime>"Jan 20 2022  5:13AM"</UnitTime>
			<UnitDetail>"Unit Cleared"</UnitDetail></units><units>
			<UnitTime>"Jan 20 2022  1:40AM"</UnitTime>
			<UnitDetail>"Unit At Scene"</UnitDetail></units><units>
			<UnitTime>"Jan 19 2022 10:24PM"</UnitTime>
			<UnitDetail>"Unit Assigned"</UnitDetail></units><units>
			<UnitTime>"Jan 20 2022  4:35AM"</UnitTime>
			<UnitDetail>"Unit Cleared"</UnitDetail></units><units>
			<UnitTime>"Jan 19 2022  9:49PM"</UnitTime>
			<UnitDetail>"Unit At Scene"</UnitDetail></units><units>
			<UnitTime>"Jan 19 2022  9:49PM"</UnitTime>
			<UnitDetail>"Unit Assigned"</UnitDetail></units><units>
			<UnitTime>"Jan 20 2022  4:00AM"</UnitTime>
			<UnitDetail>"Unit Cleared"</UnitDetail></units><units>
			<UnitTime>"Jan 19 2022  9:49PM"</UnitTime>
			<UnitDetail>"Unit At Scene"</UnitDetail></units><units>
			<UnitTime>"Jan 19 2022  9:48PM"</UnitTime>
			<UnitDetail>"Unit Assigned"</UnitDetail></units></LogDetails></Log>

		<Log ID = "220119LA02995">
			<LogTime>"Jan 19 2022  9:29PM"</LogTime>
			<LogType>"MZP-Assist CT with Maintenance"</LogType>
			<Location>"Sr134 E / Orange Grove Blvd Ofr"</Location>
			<LocationDesc>""</LocationDesc>
			<Area>"Central LA"</Area>
			<ThomasBrothers>""</ThomasBrothers>
			<LATLON>"34145538:118165551"</LATLON>
			<LogDetails><details/><units>
			<UnitTime>"Jan 20 2022  1:40AM"</UnitTime>
			<UnitDetail>"Unit At Scene"</UnitDetail></units><units>
			<UnitTime>"Jan 19 2022  9:42PM"</UnitTime>
			<UnitDetail>"Unit Enroute"</UnitDetail></units><units>
			<UnitTime>"Jan 19 2022  9:42PM"</UnitTime>
			<UnitDetail>"Unit Assigned"</UnitDetail></units><units>
			<UnitTime>"Jan 19 2022  9:31PM"</UnitTime>
			<UnitDetail>"Unit At Scene"</UnitDetail></units><units>
			<UnitTime>"Jan 19 2022  9:31PM"</UnitTime>
			<UnitDetail>"Unit Assigned"</UnitDetail></units><units>
			<UnitTime>"Jan 19 2022  9:31PM"</UnitTime>
			<UnitDetail>"Unit At Scene"</UnitDetail></units><units>
			<UnitTime>"Jan 19 2022  9:31PM"</UnitTime>
			<UnitDetail>"Unit Assigned"</UnitDetail></units></LogDetails></Log>
</Dispatch>
<Dispatch ID = "MRCC">

		<Log ID = "220120MR00039">
			<LogTime>"Jan 20 2022  5:14AM"</LogTime>
			<LogType>"1179-Trfc Collision-1141 Enrt"</LogType>
			<Location>"21797 Reynolds Ave"</Location>
			<LocationDesc>"APT F2"</LocationDesc>
			<Area>"Los Banos"</Area>
			<ThomasBrothers>""</ThomasBrothers>
			<LATLON>"36970256:120644722"</LATLON>
			<LogDetails>
		<details>
			<DetailTime>"Jan 20 2022  5:19AM"</DetailTime>
			<IncidentDetail>"[9] 1039 S2 OFC"</IncidentDetail>
		</details>
		<details>
			<DetailTime>"Jan 20 2022  5:18AM"</DetailTime>
			<IncidentDetail>"[8] UKN WHERE TC OCCD"</IncidentDetail>
		</details>
		<details>
			<DetailTime>"Jan 20 2022  5:17AM"</DetailTime>
			<IncidentDetail>"[7] 1039 CALFIRE MRI"</IncidentDetail>
		</details>
		<details>
			<DetailTime>"Jan 20 2022  5:16AM"</DetailTime>
			<IncidentDetail>"[4] 1 PTY BLEEDING/ OTHER PTY HAS LEG AND HEAD INJS"</IncidentDetail>
		</details><units>
			<UnitTime>"Jan 20 2022  5:21AM"</UnitTime>
			<UnitDetail>"Unit Enroute"</UnitDetail></units><units>
			<UnitTime>"Jan 20 2022  5:21AM"</UnitTime>
			<UnitDetail>"Unit Assigned"</UnitDetail></units></LogDetails></Log>

		<Log ID = "220120MR00038">
			<LogTime>"Jan 20 2022  5:12AM"</LogTime>
			<LogType>"1125-Traffic Hazard"</LogType>
			<Location>"Shoemake Ave / N Gates Rd"</Location>
			<LocationDesc>"EB"</LocationDesc>
			<Area>"Modesto"</Area>
			<ThomasBrothers>""</ThomasBrothers>
			<LATLON>"37666792:121159227"</LATLON>
			<LogDetails><details/><units>
			<UnitTime>"Jan 20 2022  5:19AM"</UnitTime>
			<UnitDetail>"Unit At Scene"</UnitDetail></units><units>
			<UnitTime>"Jan 20 2022  5:15AM"</UnitTime>
			<UnitDetail>"Unit Enroute"</UnitDetail></units><units>
			<UnitTime>"Jan 20 2022  5:15AM"</UnitTime>
			<UnitDetail>"Unit Assigned"</UnitDetail></units></LogDetails></Log>

		<Log ID = "220120MR00002">
			<LogTime>"Jan 20 2022 12:00AM"</LogTime>
			<LogType>"FOG-Foggy Conditions"</LogType>
			<Location>"1500 Bell Dr"</Location>
			<LocationDesc>"FOG LOG"</LocationDesc>
			<Area>"MR"</Area>
			<ThomasBrothers>""</ThomasBrothers>
			<LATLON>"37342910:120614260"</LATLON>
			<LogDetails><details/><units>
			<UnitTime>"Jan 20 2022 12:00AM"</UnitTime>
			<UnitDetail>"Unit At Scene"</UnitDetail></units><units>
			<UnitTime>"Jan 20 2022 12:00AM"</UnitTime>
			<UnitDetail>"Unit Enroute"</UnitDetail></units><units>
			<UnitTime>"Jan 20 2022 12:00AM"</UnitTime>
			<UnitDetail>"Unit Assigned"</UnitDetail></units></LogDetails></Log>

		<Log ID = "220119MR00368">
			<LogTime>"Jan 19 2022  8:46PM"</LogTime>
			<LogType>"CZP-Assist with Construction"</LogType>
			<Location>"Sr99 S / Applegate Rd"</Location>
			<LocationDesc>"SB SR99 AT"</LocationDesc>
			<Area>"Merced"</Area>
			<ThomasBrothers>""</ThomasBrothers>
			<LATLON>"37344511:120613328"</LATLON>
			<LogDetails>
		<details>
			<DetailTime>"Jan 19 2022  8:46PM"</DetailTime>
			<IncidentDetail>"[1] ONR AND OFR WILL BE CLOSED"</IncidentDetail>
		</details><units>
			<UnitTime>"Jan 19 2022  8:47PM"</UnitTime>
			<UnitDetail>"Unit At Scene"</UnitDetail></units><units>
			<UnitTime>"Jan 19 2022  8:47PM"</UnitTime>
			<UnitDetail>"Unit Assigned"</UnitDetail></units></LogDetails></Log>

		<Log ID = "220119MR00168">
			<LogTime>"Jan 19 2022  1:12PM"</LogTime>
			<LogType>"SILVER Alert"</LogType>
			<Location>"1500 Bell Dr"</Location>
			<LocationDesc>"FOR MERCED  COUNTY"</LocationDesc>
			<Area>"MR"</Area>
			<ThomasBrothers>""</ThomasBrothers>
			<LATLON>"37342910:120614260"</LATLON>
			<LogDetails><details/><units>
			<UnitTime>"Jan 19 2022  8:08PM"</UnitTime>
			<UnitDetail>"Unit Cleared"</UnitDetail></units><units>
			<UnitTime>"Jan 19 2022  8:07PM"</UnitTime>
			<UnitDetail>"Unit Assigned"</UnitDetail></units></LogDetails></Log>
</Dispatch>
<Dispatch ID = "FRCC">

		<Log ID = "220120FR00015">
			<LogTime>"Jan 20 2022 12:40AM"</LogTime>
			<LogType>"CHAINS-Chain Control"</LogType>
			<Location>"1380 E Fortune Ave"</Location>
			<LocationDesc>"CHAINS LOG"</LocationDesc>
			<Area>"FR"</Area>
			<ThomasBrothers>""</ThomasBrothers>
			<LATLON>"36689097:119764090"</LATLON>
			<LogDetails><details/><units>
			<UnitTime>"Jan 20 2022 12:40AM"</UnitTime>
			<UnitDetail>"Unit At Scene"</UnitDetail></units><units>
			<UnitTime>"Jan 20 2022 12:40AM"</UnitTime>
			<UnitDetail>"Unit Enroute"</UnitDetail></units><units>
			<UnitTime>"Jan 20 2022 12:40AM"</UnitTime>
			<UnitDetail>"Unit Assigned"</UnitDetail></units></LogDetails></Log>

		<Log ID = "220120FR00012">
			<LogTime>"Jan 20 2022 12:39AM"</LogTime>
			<LogType>"FOG-Foggy Conditions"</LogType>
			<Location>"1380 E Fortune Ave"</Location>
			<LocationDesc>"FOG LOG"</LocationDesc>
			<Area>"FR"</Area>
			<ThomasBrothers>""</ThomasBrothers>
			<LATLON>"36689097:119764090"</LATLON>
			<LogDetails><details/><units>
			<UnitTime>"Jan 20 2022 12:39AM"</UnitTime>
			<UnitDetail>"Unit At Scene"</UnitDetail></units><units>
			<UnitTime>"Jan 20 2022 12:39AM"</UnitTime>
			<UnitDetail>"Unit Enroute"</UnitDetail></units><units>
			<UnitTime>"Jan 20 2022 12:39AM"</UnitTime>
			<UnitDetail>"Unit Assigned"</UnitDetail></units></LogDetails></Log>
</Dispatch>
<Dispatch ID = "BFCC">

		<Log ID = "220120BF00001">
			<LogTime>"Jan 20 2022 12:00AM"</LogTime>
			<LogType>"FOG-Foggy Conditions"</LogType>
			<Location>"Bakersfield Fog Log"</Location>
			<LocationDesc>""</LocationDesc>
			<Area>"BF"</Area>
			<ThomasBrothers>""</ThomasBrothers>
			<LATLON>"35265234:119024794"</LATLON>
			<LogDetails><details/><units>
			<UnitTime>"Jan 20 2022 12:01AM"</UnitTime>
			<UnitDetail>"Unit At Scene"</UnitDetail></units><units>
			<UnitTime>"Jan 20 2022 12:01AM"</UnitTime>
			<UnitDetail>"Unit Assigned"</UnitDetail></units></LogDetails></Log>
</Dispatch>
</Center>

<Center ID = "INHB">
<Dispatch ID = "ICCC">

		<Log ID = "220120IC00032">
			<LogTime>"Jan 20 2022  5:18AM"</LogTime>
			<LogType>"1125-Traffic Hazard"</LogType>
			<Location>"I10 E Eo / 30 Mile Curve Mm 126"</Location>
			<LocationDesc>"I10 E EO 30 Mile Curve  MM 126"</LocationDesc>
			<Area>"Blythe"</Area>
			<ThomasBrothers>""</ThomasBrothers>
			<LATLON>"33625441:115054566"</LATLON>
			<LogDetails>
		<details>
			<DetailTime>"Jan 20 2022  5:19AM"</DetailTime>
			<IncidentDetail>"[4] 2 OTHER VEHS ON THE RHS"</IncidentDetail>
		</details>
		<details>
			<DetailTime>"Jan 20 2022  5:19AM"</DetailTime>
			<IncidentDetail>"[2] HIT WOOD DEBRIS"</IncidentDetail>
		</details><units>
			<UnitTime>"Jan 20 2022  5:21AM"</UnitTime>
			<UnitDetail>"Unit Assigned"</UnitDetail></units></LogDetails></Log>

		<Log ID = "220120IC00031">
			<LogTime>"Jan 20 2022  5:15AM"</LogTime>
			<LogType>"1182-Trfc Collision-No Inj"</LogType>
			<Location>"I10 W / Cactus City  Ra Exit 159 Ccra Mm 72"</Location>
			<LocationDesc>"I10 W Cactus City RA Exit 159 CCRA MM 72"</LocationDesc>
			<Area>"Indio"</Area>
			<ThomasBrothers>""</ThomasBrothers>
			<LATLON>"33678906:115965835"</LATLON>
			<LogDetails>
		<details>
			<DetailTime>"Jan 20 2022  5:21AM"</DetailTime>
			<IncidentDetail>"[10] [Appended, 05:22:07] [6] HIS WIFE WAS DRIVING WHILE HE SLEPT HE IS UNABLE TO SAY WEATHER OR NOT THERE UIS A T/C"</IncidentDetail>
		</details>
		<details>
			<DetailTime>"Jan 20 2022  5:20AM"</DetailTime>
			<IncidentDetail>"[7] [Appended, 05:22:07] [3] OTHER VEH  BRO/WHI KW WHI REFER"</IncidentDetail>
		</details><units>
			<UnitTime>"Jan 20 2022  5:20AM"</UnitTime>
			<UnitDetail>"Unit Assigned"</UnitDetail></units></LogDetails></Log>

		<Log ID = "220119IC00261">
			<LogTime>"Jan 19 2022  6:32PM"</LogTime>
			<LogType>"CZP-Assist with Construction"</LogType>
			<Location>"I10 E EO / HIGHLAND SPRINGS AV"</Location>
			<LocationDesc>"BANNING"</LocationDesc>
			<Area>"San Gorgonio Pass"</Area>
			<ThomasBrothers>""</ThomasBrothers>
			<LATLON>"33926579:116941701"</LATLON>
			<LogDetails>
		<details>
			<DetailTime>"Jan 19 2022  7:25PM"</DetailTime>
			<IncidentDetail>"[3] 97-R21  #2 AND #3 LANE IS CLOSED"</IncidentDetail>
		</details>
		<details>
			<DetailTime>"Jan 19 2022  7:00PM"</DetailTime>
			<IncidentDetail>"[1] 97-R21  RUNNING A BREAK EB 10 AT BEAUMONT"</IncidentDetail>
		</details><units>
			<UnitTime>"Jan 19 2022 11:23PM"</UnitTime>
			<UnitDetail>"Unit At Scene"</UnitDetail></units><units>
			<UnitTime>"Jan 19 2022 11:07PM"</UnitTime>
			<UnitDetail>"Unit Enroute"</UnitDetail></units><units>
			<UnitTime>"Jan 19 2022 11:07PM"</UnitTime>
			<UnitDetail>"Unit Assigned"</UnitDetail></units><units>
			<UnitTime>"Jan 20 2022 12:03AM"</UnitTime>
			<UnitDetail>"Unit Cleared"</UnitDetail></units><units>
			<UnitTime>"Jan 19 2022 10:52PM"</UnitTime>
			<UnitDetail>"Unit Assigned"</UnitDetail></units><units>
			<UnitTime>"Jan 20 2022  4:48AM"</UnitTime>
			<UnitDetail>"Unit Cleared"</UnitDetail></units><units>
			<UnitTime>"Jan 19 2022 11:00PM"</UnitTime>
			<UnitDetail>"Unit At Scene"</UnitDetail></units><units>
			<UnitTime>"Jan 19 2022 10:45PM"</UnitTime>
			<UnitDetail>"Unit Assigned"</UnitDetail></units><units>
			<UnitTime>"Jan 19 2022 10:42PM"</UnitTime>
			<UnitDetail>"Unit Cleared"</UnitDetail></units><units>
			<UnitTime>"Jan 19 2022 10:40PM"</UnitTime>
			<UnitDetail>"Unit Assigned"</UnitDetail></units><units>
			<UnitTime>"Jan 19 2022 10:30PM"</UnitTime>
			<UnitDetail>"Unit Cleared"</UnitDetail></units><units>
			<UnitTime>"Jan 19 2022  7:33PM"</UnitTime>
			<UnitDetail>"Unit At Scene"</UnitDetail></units><units>
			<UnitTime>"Jan 19 2022  6:32PM"</UnitTime>
			<UnitDetail>"Unit Assigned"</UnitDetail></units></LogDetails></Log>

		<Log ID = "220119IC00038">
			<LogTime>"Jan 19 2022  4:23AM"</LogTime>
			<LogType>"1013-Road/Weather Conditions"</LogType>
			<Location>"79650 Varner Rd"</Location>
			<LocationDesc>"WEATHER LOG ** WEDNESDAY**"</LocationDesc>
			<Area>"IC"</Area>
			<ThomasBrothers>""</ThomasBrothers>
			<LATLON>"33751459:116272108"</LATLON>
			<LogDetails>
		<details>
			<DetailTime>"Jan 19 2022  5:38PM"</DetailTime>
			<IncidentDetail>"[5] [CHP] has closed their incident [220119OC00293]"</IncidentDetail>
		</details>
		<details>
			<DetailTime>"Jan 19 2022  5:02PM"</DetailTime>
			<IncidentDetail>"[3] [CHP] has closed their incident [220119OC00321]"</IncidentDetail>
		</details><units>
			<UnitTime>"Jan 19 2022  4:23AM"</UnitTime>
			<UnitDetail>"Unit At Scene"</UnitDetail></units><units>
			<UnitTime>"Jan 19 2022  4:23AM"</UnitTime>
			<UnitDetail>"Unit Assigned"</UnitDetail></units></LogDetails></Log>
</Dispatch>
<Dispatch ID = "INCC">

		<Log ID = "220120IN00101">
			<LogTime>"Jan 20 2022  4:59AM"</LogTime>
			<LogType>"1183-Trfc Collision-Unkn Inj"</LogType>
			<Location>"I405 S / Western Ave Ofr"</Location>
			<LocationDesc>"SB 405 JNO  WESTERN"</LocationDesc>
			<Area>" LACC"</Area>
			<ThomasBrothers>""</ThomasBrothers>
			<LATLON>"33860625:118313721"</LATLON>
			<LogDetails>
		<details>
			<DetailTime>"Jan 20 2022  5:05AM"</DetailTime>
			<IncidentDetail>"[13] PRTYS O/O VEH ON RS"</IncidentDetail>
		</details>
		<details>
			<DetailTime>"Jan 20 2022  5:04AM"</DetailTime>
			<IncidentDetail>"[11] ***VEHS BLKNG RIGHT HAND LN***"</IncidentDetail>
		</details>
		<details>
			<DetailTime>"Jan 20 2022  5:01AM"</DetailTime>
			<IncidentDetail>"[2] WHI FORD WAS 1126 ON RS WHEN ADDTL VEH TCD INTO HER"</IncidentDetail>
		</details>
		<details>
			<DetailTime>"Jan 20 2022  5:01AM"</DetailTime>
			<IncidentDetail>"[1] WHI FORD CMAX VS UNK"</IncidentDetail>
		</details></LogDetails></Log>

		<Log ID = "220120IN00096">
			<LogTime>"Jan 20 2022  4:51AM"</LogTime>
			<LogType>"1183-Trfc Collision-Unkn Inj"</LogType>
			<Location>"San Bernardino Ave / Cherry Ave"</Location>
			<LocationDesc>"JWO"</LocationDesc>
			<Area>"Rancho Cucamonga"</Area>
			<ThomasBrothers>""</ThomasBrothers>
			<LATLON>"34077281:117488777"</LATLON>
			<LogDetails>
		<details>
			<DetailTime>"Jan 20 2022  5:09AM"</DetailTime>
			<IncidentDetail>"[15] NEG VEH VS FENCE"</IncidentDetail>
		</details>
		<details>
			<DetailTime>"Jan 20 2022  5:09AM"</DetailTime>
			<IncidentDetail>"[14] C123-153  VEH DOWN EMBANKMENT WB SAN BERNARDINO JWO CHERRY"</IncidentDetail>
		</details>
		<details>
			<DetailTime>"Jan 20 2022  5:05AM"</DetailTime>
			<IncidentDetail>"[12] 1039 DIETZ TOW ENRT 909-986-2703 Pub"</IncidentDetail>
		</details>
		<details>
			<DetailTime>"Jan 20 2022  5:04AM"</DetailTime>
			<IncidentDetail>"[11] C123-153 REQ 1185 FB"</IncidentDetail>
		</details>
		<details>
			<DetailTime>"Jan 20 2022  5:04AM"</DetailTime>
			<IncidentDetail>"[10] PER DUP -- VEH DOWN DITCH AND INTO FENCE"</IncidentDetail>
		</details>
		<details>
			<DetailTime>"Jan 20 2022  4:53AM"</DetailTime>
			<IncidentDetail>"[6] VEH HIT FENCE OF KAISER STEEL"</IncidentDetail>
		</details>
		<details>
			<DetailTime>"Jan 20 2022  4:53AM"</DetailTime>
			<IncidentDetail>"[5] NEG BLOCKING"</IncidentDetail>
		</details>
		<details>
			<DetailTime>"Jan 20 2022  4:52AM"</DetailTime>
			<IncidentDetail>"[2] VEH VS FENCE"</IncidentDetail>
		</details><units>
			<UnitTime>"Jan 20 2022  5:08AM"</UnitTime>
			<UnitDetail>"Unit At Scene"</UnitDetail></units><units>
			<UnitTime>"Jan 20 2022  5:00AM"</UnitTime>
			<UnitDetail>"Unit Assigned"</UnitDetail></units></LogDetails></Log>

		<Log ID = "220120IN00084">
			<LogTime>"Jan 20 2022  4:26AM"</LogTime>
			<LogType>"1013-Road/Weather Conditions"</LogType>
			<Location>"Media Log"</Location>
			<LocationDesc>"INLAND DIVISION SUMMARY LOG"</LocationDesc>
			<Area>""</Area>
			<ThomasBrothers>""</ThomasBrothers>
			<LATLON>"0:0"</LATLON>
			<LogDetails>
		<details>
			<DetailTime>"Jan 20 2022  4:28AM"</DetailTime>
			<IncidentDetail>"[1] *MEDIA LINE IS OPEN (909)356-3712*"</IncidentDetail>
		</details></LogDetails></Log>

		<Log ID = "220120IN00045">
			<LogTime>"Jan 20 2022  2:39AM"</LogTime>
			<LogType>"1125-Traffic Hazard"</LogType>
			<Location>"I10 W EO / MILLS AVE"</Location>
			<LocationDesc>"****1015"</LocationDesc>
			<Area>"Rancho Cucamonga"</Area>
			<ThomasBrothers>""</ThomasBrothers>
			<LATLON>"34081918:117707082"</LATLON>
			<LogDetails>
		<details>
			<DetailTime>"Jan 20 2022  4:06AM"</DetailTime>
			<IncidentDetail>"[48] [Notification] [CHP]-BT ETA 15-20 MINS ETA TO RANCHO OFC"</IncidentDetail>
		</details>
		<details>
			<DetailTime>"Jan 20 2022  3:59AM"</DetailTime>
			<IncidentDetail>"[46]  1039 BT"</IncidentDetail>
		</details>
		<details>
			<DetailTime>"Jan 20 2022  3:44AM"</DetailTime>
			<IncidentDetail>"[38] [Notification] [CHP]-PER NMSP REMARKS: WARRANT IS NOT CONFIRMED. WE WILL NOT EXTRADITE FROM CALIFORNIA - 1039 NMSP THEY ADV WARRANT IS ACTIVE BY THEY WILL NOT EXTRADITE AND CANNOT CITE PTY
"</IncidentDetail>
		</details>
		<details>
			<DetailTime>"Jan 20 2022  3:21AM"</DetailTime>
			<IncidentDetail>"[33] [Notification] [CHP]-1039 NM STATE POLICE 505 863-9353 - THEY ADV CANT DO CONFIRMATION BY PHONE - WILL NEED TO SEND THRU CLETS - LINK SENDING HIT CONFIRMATION NOW"</IncidentDetail>
		</details>
		<details>
			<DetailTime>"Jan 20 2022  3:00AM"</DetailTime>
			<IncidentDetail>"[23] PRO TOW CPYS 1020"</IncidentDetail>
		</details>
		<details>
			<DetailTime>"Jan 20 2022  2:55AM"</DetailTime>
			<IncidentDetail>"[19] PRO TOW CPYS EXP"</IncidentDetail>
		</details>
		<details>
			<DetailTime>"Jan 20 2022  2:54AM"</DetailTime>
			<IncidentDetail>"[18] [Rotation Request Comment] 1039 PRO TOW IN 909-517-3400*************"</IncidentDetail>
		</details>
		<details>
			<DetailTime>"Jan 20 2022  2:53AM"</DetailTime>
			<IncidentDetail>"[16] C123-103  REQ 1185 ROT"</IncidentDetail>
		</details>
		<details>
			<DetailTime>"Jan 20 2022  2:39AM"</DetailTime>
			<IncidentDetail>"[2] UNK SMALL CAR BLOCKING SLOW LN"</IncidentDetail>
		</details><units>
			<UnitTime>"Jan 20 2022  2:41AM"</UnitTime>
			<UnitDetail>"Unit Assigned"</UnitDetail></units></LogDetails></Log>

		<Log ID = "220119IN01044">
			<LogTime>"Jan 19 2022  9:16PM"</LogTime>
			<LogType>"CLOSURE of a Road"</LogType>
			<Location>"Sr60 W To / I15 S Con"</Location>
			<LocationDesc>"SR60 W TO I15 S CON** UNMANNED**"</LocationDesc>
			<Area>"Riverside"</Area>
			<ThomasBrothers>""</ThomasBrothers>
			<LATLON>"34021693:117548738"</LATLON>
			<LogDetails>
		<details>
			<DetailTime>"Jan 19 2022  9:17PM"</DetailTime>
			<IncidentDetail>"[1] UNMANNED CLOSURE"</IncidentDetail>
		</details></LogDetails></Log>

		<Log ID = "220119IN01012">
			<LogTime>"Jan 19 2022  8:33PM"</LogTime>
			<LogType>"CLOSURE of a Road"</LogType>
			<Location>"I10 W TO / I215 S CON"</Location>
			<LocationDesc>"I10 W TO I215 S CON"</LocationDesc>
			<Area>"San Bernardino"</Area>
			<ThomasBrothers>""</ThomasBrothers>
			<LATLON>"34064388:117294186"</LATLON>
			<LogDetails>
		<details>
			<DetailTime>"Jan 20 2022  5:23AM"</DetailTime>
			<IncidentDetail>"[8] [Notification] [CHP]-Problem changed from TADV-Traffic Advisory to CLOSURE of a Road by CHP"</IncidentDetail>
		</details>
		<details>
			<DetailTime>"Jan 19 2022  9:02PM"</DetailTime>
			<IncidentDetail>"[6] 215 AT WASHINGTON OVER PASS CLOSED"</IncidentDetail>
		</details>
		<details>
			<DetailTime>"Jan 19 2022  9:01PM"</DetailTime>
			<IncidentDetail>"[5] 215 S CLOSED"</IncidentDetail>
		</details>
		<details>
			<DetailTime>"Jan 19 2022  8:33PM"</DetailTime>
			<IncidentDetail>"[3] NB AND SB AT WA BRIDGE CLOSED"</IncidentDetail>
		</details></LogDetails></Log>

		<Log ID = "220119IN00994">
			<LogTime>"Jan 19 2022  8:14PM"</LogTime>
			<LogType>"CLOSURE of a Road"</LogType>
			<Location>"I15 N / Ontario Ave"</Location>
			<LocationDesc>"ONT TO MAG *UNMANNED CLOSURE"</LocationDesc>
			<Area>"Riverside"</Area>
			<ThomasBrothers>""</ThomasBrothers>
			<LATLON>"33843553:117534695"</LATLON>
			<LogDetails>
		<details>
			<DetailTime>"Jan 19 2022  8:14PM"</DetailTime>
			<IncidentDetail>"[2] [Notification] [CHP]-Problem changed from INFO-Information to CLOSURE of a Road by CHP"</IncidentDetail>
		</details>
		<details>
			<DetailTime>"Jan 19 2022  8:14PM"</DetailTime>
			<IncidentDetail>"[1] ,UNMANNED CLOSURE #3 LN --- ALSO,  ONTARIO ONR AND MAGNOLIA OFR CLOSED"</IncidentDetail>
		</details><units>
			<UnitTime>"Jan 19 2022  8:15PM"</UnitTime>
			<UnitDetail>"Unit Cleared"</UnitDetail></units><units>
			<UnitTime>"Jan 19 2022  8:14PM"</UnitTime>
			<UnitDetail>"Unit At Scene"</UnitDetail></units><units>
			<UnitTime>"Jan 19 2022  8:14PM"</UnitTime>
			<UnitDetail>"Unit Enroute"</UnitDetail></units><units>
			<UnitTime>"Jan 19 2022  8:14PM"</UnitTime>
			<UnitDetail>"Unit Assigned"</UnitDetail></units></LogDetails></Log>

		<Log ID = "220119IN00949">
			<LogTime>"Jan 19 2022  7:19PM"</LogTime>
			<LogType>"CLOSURE of a Road"</LogType>
			<Location>"I215 N / WASHINGTON ST"</Location>
			<LocationDesc>"I215 N BARTON RD"</LocationDesc>
			<Area>"San Bernardino"</Area>
			<ThomasBrothers>""</ThomasBrothers>
			<LATLON>"34047511:117307526"</LATLON>
			<LogDetails>
		<details>
			<DetailTime>"Jan 20 2022  5:00AM"</DetailTime>
			<IncidentDetail>"[9] 75-CZP3  SB LANES OPEN"</IncidentDetail>
		</details>
		<details>
			<DetailTime>"Jan 20 2022  4:40AM"</DetailTime>
			<IncidentDetail>"[8] 75-CZP4  WB 10 TO SB 215 OPEN"</IncidentDetail>
		</details>
		<details>
			<DetailTime>"Jan 19 2022  9:01PM"</DetailTime>
			<IncidentDetail>"[5] [Notification] [CHP]-Problem changed from INFO-Information to CLOSURE of a Road by CHP"</IncidentDetail>
		</details>
		<details>
			<DetailTime>"Jan 19 2022  9:01PM"</DetailTime>
			<IncidentDetail>"[4] SB 215 CLOSED"</IncidentDetail>
		</details>
		<details>
			<DetailTime>"Jan 19 2022  8:32PM"</DetailTime>
			<IncidentDetail>"[3] EB 10 TO SB 215 CLOSED"</IncidentDetail>
		</details>
		<details>
			<DetailTime>"Jan 19 2022  8:32PM"</DetailTime>
			<IncidentDetail>"[2] WB 10 TO SB 215 IS CLOSED"</IncidentDetail>
		</details>
		<details>
			<DetailTime>"Jan 19 2022  7:19PM"</DetailTime>
			<IncidentDetail>"[1] NB  AND SB 215 AT WASHINGTON BRIDGE CLOSURE"</IncidentDetail>
		</details><units>
			<UnitTime>"Jan 20 2022  5:09AM"</UnitTime>
			<UnitDetail>"Unit Cleared"</UnitDetail></units><units>
			<UnitTime>"Jan 19 2022 10:49PM"</UnitTime>
			<UnitDetail>"Unit At Scene"</UnitDetail></units><units>
			<UnitTime>"Jan 19 2022  9:58PM"</UnitTime>
			<UnitDetail>"Unit Assigned"</UnitDetail></units><units>
			<UnitTime>"Jan 19 2022 11:05PM"</UnitTime>
			<UnitDetail>"Unit Cleared"</UnitDetail></units><units>
			<UnitTime>"Jan 19 2022 10:49PM"</UnitTime>
			<UnitDetail>"Unit At Scene"</UnitDetail></units><units>
			<UnitTime>"Jan 19 2022  9:58PM"</UnitTime>
			<UnitDetail>"Unit Assigned"</UnitDetail></units><units>
			<UnitTime>"Jan 19 2022 11:02PM"</UnitTime>
			<UnitDetail>"Unit Cleared"</UnitDetail></units><units>
			<UnitTime>"Jan 19 2022 10:49PM"</UnitTime>
			<UnitDetail>"Unit At Scene"</UnitDetail></units><units>
			<UnitTime>"Jan 19 2022  9:39PM"</UnitTime>
			<UnitDetail>"Unit Assigned"</UnitDetail></units><units>
			<UnitTime>"Jan 20 2022  5:10AM"</UnitTime>
			<UnitDetail>"Unit Cleared"</UnitDetail></units><units>
			<UnitTime>"Jan 19 2022  8:23PM"</UnitTime>
			<UnitDetail>"Unit At Scene"</UnitDetail></units><units>
			<UnitTime>"Jan 19 2022  8:22PM"</UnitTime>
			<UnitDetail>"Unit Enroute"</UnitDetail></units><units>
			<UnitTime>"Jan 19 2022  8:22PM"</UnitTime>
			<UnitDetail>"Unit Assigned"</UnitDetail></units><units>
			<UnitTime>"Jan 19 2022 10:49PM"</UnitTime>
			<UnitDetail>"Unit At Scene"</UnitDetail></units><units>
			<UnitTime>"Jan 19 2022  7:24PM"</UnitTime>
			<UnitDetail>"Unit Assigned"</UnitDetail></units><units>
			<UnitTime>"Jan 20 2022  5:07AM"</UnitTime>
			<UnitDetail>"Unit Cleared"</UnitDetail></units><units>
			<UnitTime>"Jan 19 2022 10:48PM"</UnitTime>
			<UnitDetail>"Unit At Scene"</UnitDetail></units><units>
			<UnitTime>"Jan 19 2022  7:24PM"</UnitTime>
			<UnitDetail>"Unit Assigned"</UnitDetail></units><units>
			<UnitTime>"Jan 20 2022  5:06AM"</UnitTime>
			<UnitDetail>"Unit Cleared"</UnitDetail></units><units>
			<UnitTime>"Jan 19 2022 10:48PM"</UnitTime>
			<UnitDetail>"Unit At Scene"</UnitDetail></units><units>
			<UnitTime>"Jan 19 2022  7:24PM"</UnitTime>
			<UnitDetail>"Unit Assigned"</UnitDetail></units><units>
			<UnitTime>"Jan 19 2022 10:48PM"</UnitTime>
			<UnitDetail>"Unit At Scene"</UnitDetail></units><units>
			<UnitTime>"Jan 19 2022  7:24PM"</UnitTime>
			<UnitDetail>"Unit Assigned"</UnitDetail></units><units>
			<UnitTime>"Jan 20 2022  5:10AM"</UnitTime>
			<UnitDetail>"Unit Cleared"</UnitDetail></units><units>
			<UnitTime>"Jan 19 2022  7:19PM"</UnitTime>
			<UnitDetail>"Unit At Scene"</UnitDetail></units><units>
			<UnitTime>"Jan 19 2022  7:19PM"</UnitTime>
			<UnitDetail>"Unit Enroute"</UnitDetail></units><units>
			<UnitTime>"Jan 19 2022  7:19PM"</UnitTime>
			<UnitDetail>"Unit Assigned"</UnitDetail></units></LogDetails></Log>
</Dispatch>
<Dispatch ID = "BSCC">

		<Log ID = "220120BS00027">
			<LogTime>"Jan 20 2022  4:54AM"</LogTime>
			<LogType>"1125-Traffic Hazard"</LogType>
			<Location>"I15 S / Ranchero Rd"</Location>
			<LocationDesc>"SB JSO"</LocationDesc>
			<Area>"Victorville"</Area>
			<ThomasBrothers>""</ThomasBrothers>
			<LATLON>"34382913:117415565"</LATLON>
			<LogDetails>
		<details>
			<DetailTime>"Jan 20 2022  5:22AM"</DetailTime>
			<IncidentDetail>"[7] 81 -- VEH ON HOOK"</IncidentDetail>
		</details>
		<details>
			<DetailTime>"Jan 20 2022  4:57AM"</DetailTime>
			<IncidentDetail>"[5] 1039 1185"</IncidentDetail>
		</details>
		<details>
			<DetailTime>"Jan 20 2022  4:56AM"</DetailTime>
			<IncidentDetail>"[4] C12-081  VEH MISSING LEFT FRONT TIRE"</IncidentDetail>
		</details>
		<details>
			<DetailTime>"Jan 20 2022  4:55AM"</DetailTime>
			<IncidentDetail>"[2] [Rotation Request Comment] 1039 AGUIARS // 760 981 4905"</IncidentDetail>
		</details>
		<details>
			<DetailTime>"Jan 20 2022  4:54AM"</DetailTime>
			<IncidentDetail>"[1] ,,SIL INFI REQ 1185 PART 1125 IN NUM 5 LN"</IncidentDetail>
		</details><units>
			<UnitTime>"Jan 20 2022  5:25AM"</UnitTime>
			<UnitDetail>"Unit Cleared"</UnitDetail></units><units>
			<UnitTime>"Jan 20 2022  4:54AM"</UnitTime>
			<UnitDetail>"Unit At Scene"</UnitDetail></units><units>
			<UnitTime>"Jan 20 2022  4:54AM"</UnitTime>
			<UnitDetail>"Unit Enroute"</UnitDetail></units><units>
			<UnitTime>"Jan 20 2022  4:54AM"</UnitTime>
			<UnitDetail>"Unit Assigned"</UnitDetail></units></LogDetails></Log>
</Dispatch>
<Dispatch ID = "BCCC">

		<Log ID = "220120BC00079">
			<LogTime>"Jan 20 2022  3:54AM"</LogTime>
			<LogType>"1179-Trfc Collision-1141 Enrt"</LogType>
			<Location>"Sr76 / Rice Canyon Rd"</Location>
			<LocationDesc>"JWO"</LocationDesc>
			<Area>"Oceanside"</Area>
			<ThomasBrothers>""</ThomasBrothers>
			<LATLON>"33342893:117132931"</LATLON>
			<LogDetails>
		<details>
			<DetailTime>"Jan 20 2022  4:28AM"</DetailTime>
			<IncidentDetail>"[15] 1039 ROADWAY TOW"</IncidentDetail>
		</details>
		<details>
			<DetailTime>"Jan 20 2022  4:27AM"</DetailTime>
			<IncidentDetail>"[14] C92-015C  80 FT OFF THE RDWY DOWN 30 FT EMBANKMENT"</IncidentDetail>
		</details>
		<details>
			<DetailTime>"Jan 20 2022  4:02AM"</DetailTime>
			<IncidentDetail>"[11] [Rotation Request Comment] 1039 ROADWAY TOW WITH RECOVERY TRUCK 760-747-3335 XXXXXXXX"</IncidentDetail>
		</details>
		<details>
			<DetailTime>"Jan 20 2022  4:01AM"</DetailTime>
			<IncidentDetail>"[10] 23C; 1185 RECOVERY TOW"</IncidentDetail>
		</details>
		<details>
			<DetailTime>"Jan 20 2022  3:59AM"</DetailTime>
			<IncidentDetail>"[8] 1039 CALIFRE SD"</IncidentDetail>
		</details>
		<details>
			<DetailTime>"Jan 20 2022  3:56AM"</DetailTime>
			<IncidentDetail>"[3] DRIVER OO VEH"</IncidentDetail>
		</details>
		<details>
			<DetailTime>"Jan 20 2022  3:56AM"</DetailTime>
			<IncidentDetail>"[2] OFF THE ROAD INTO RIVER"</IncidentDetail>
		</details><units>
			<UnitTime>"Jan 20 2022  4:20AM"</UnitTime>
			<UnitDetail>"Unit At Scene"</UnitDetail></units><units>
			<UnitTime>"Jan 20 2022  4:09AM"</UnitTime>
			<UnitDetail>"Unit Assigned"</UnitDetail></units><units>
			<UnitTime>"Jan 20 2022  4:18AM"</UnitTime>
			<UnitDetail>"Unit At Scene"</UnitDetail></units><units>
			<UnitTime>"Jan 20 2022  4:01AM"</UnitTime>
			<UnitDetail>"Unit Assigned"</UnitDetail></units></LogDetails></Log>

		<Log ID = "220120BC00059">
			<LogTime>"Jan 20 2022  2:32AM"</LogTime>
			<LogType>"1179-Trfc Collision-1141 Enrt"</LogType>
			<Location>"8824 Noeline Ave"</Location>
			<LocationDesc>""</LocationDesc>
			<Area>"El Cajon"</Area>
			<ThomasBrothers>""</ThomasBrothers>
			<LATLON>"32704951:117016285"</LATLON>
			<LogDetails>
		<details>
			<DetailTime>"Jan 20 2022  4:09AM"</DetailTime>
			<IncidentDetail>"[25] [Notification] [CHP]-CFP ETA 10-15MINS"</IncidentDetail>
		</details>
		<details>
			<DetailTime>"Jan 20 2022  4:02AM"</DetailTime>
			<IncidentDetail>"[24] 1039 BT"</IncidentDetail>
		</details>
		<details>
			<DetailTime>"Jan 20 2022  3:50AM"</DetailTime>
			<IncidentDetail>"[18] 108-S4  VEH IN TOW"</IncidentDetail>
		</details>
		<details>
			<DetailTime>"Jan 20 2022  3:28AM"</DetailTime>
			<IncidentDetail>"[13] [Rotation Request Comment] 1039 QUALITY TOW XXX 619-460-2444 XXX"</IncidentDetail>
		</details>
		<details>
			<DetailTime>"Jan 20 2022  3:27AM"</DetailTime>
			<IncidentDetail>"[12] C108-027C  1015 / 1185"</IncidentDetail>
		</details>
		<details>
			<DetailTime>"Jan 20 2022  2:40AM"</DetailTime>
			<IncidentDetail>"[8] [Notification] [CHP]-Problem changed from 1183-Trfc Collision-Unkn Inj to 1179-Trfc Collision-1141 Enrt by CHP"</IncidentDetail>
		</details>
		<details>
			<DetailTime>"Jan 20 2022  2:36AM"</DetailTime>
			<IncidentDetail>"[4] SDSO ADVS FD WILL NOT RESPOND UNTIL WE CONFIRM IF SOMEONE IS IN VEH"</IncidentDetail>
		</details>
		<details>
			<DetailTime>"Jan 20 2022  2:35AM"</DetailTime>
			<IncidentDetail>"[3] CORRECTION LINE 1 VEH VS WALL"</IncidentDetail>
		</details>
		<details>
			<DetailTime>"Jan 20 2022  2:33AM"</DetailTime>
			<IncidentDetail>"[1] VEH TC WALL"</IncidentDetail>
		</details><units>
			<UnitTime>"Jan 20 2022  3:51AM"</UnitTime>
			<UnitDetail>"Unit Assigned"</UnitDetail></units><units>
			<UnitTime>"Jan 20 2022  3:50AM"</UnitTime>
			<UnitDetail>"Unit Cleared"</UnitDetail></units><units>
			<UnitTime>"Jan 20 2022  3:25AM"</UnitTime>
			<UnitDetail>"Unit At Scene"</UnitDetail></units><units>
			<UnitTime>"Jan 20 2022  3:25AM"</UnitTime>
			<UnitDetail>"Unit Enroute"</UnitDetail></units><units>
			<UnitTime>"Jan 20 2022  3:25AM"</UnitTime>
			<UnitDetail>"Unit Assigned"</UnitDetail></units><units>
			<UnitTime>"Jan 20 2022  2:45AM"</UnitTime>
			<UnitDetail>"Unit At Scene"</UnitDetail></units><units>
			<UnitTime>"Jan 20 2022  2:45AM"</UnitTime>
			<UnitDetail>"Unit Enroute"</UnitDetail></units><units>
			<UnitTime>"Jan 20 2022  2:38AM"</UnitTime>
			<UnitDetail>"Unit Assigned"</UnitDetail></units></LogDetails></Log>

		<Log ID = "220119BC01185">
			<LogTime>"Jan 19 2022  8:51PM"</LogTime>
			<LogType>"CZP-Assist with Construction"</LogType>
			<Location>"I5 N / Manchester No"</Location>
			<LocationDesc>"BTWN MANCH - PAR"</LocationDesc>
			<Area>"Oceanside"</Area>
			<ThomasBrothers>""</ThomasBrothers>
			<LATLON>"33014072:117268699"</LATLON>
			<LogDetails><details/><units>
			<UnitTime>"Jan 19 2022  8:51PM"</UnitTime>
			<UnitDetail>"Unit At Scene"</UnitDetail></units><units>
			<UnitTime>"Jan 19 2022  8:51PM"</UnitTime>
			<UnitDetail>"Unit Enroute"</UnitDetail></units><units>
			<UnitTime>"Jan 19 2022  8:51PM"</UnitTime>
			<UnitDetail>"Unit Assigned"</UnitDetail></units></LogDetails></Log>

		<Log ID = "220119BC01157">
			<LogTime>"Jan 19 2022  8:15PM"</LogTime>
			<LogType>"CZP-Assist with Construction"</LogType>
			<Location>"I5 S / Las Flores"</Location>
			<LocationDesc>"TILL 0600"</LocationDesc>
			<Area>"Oceanside"</Area>
			<ThomasBrothers>""</ThomasBrothers>
			<LATLON>"33170706:117346691"</LATLON>
			<LogDetails><details/><units>
			<UnitTime>"Jan 20 2022  5:18AM"</UnitTime>
			<UnitDetail>"Unit Cleared"</UnitDetail></units><units>
			<UnitTime>"Jan 19 2022  9:27PM"</UnitTime>
			<UnitDetail>"Unit At Scene"</UnitDetail></units><units>
			<UnitTime>"Jan 19 2022  8:38PM"</UnitTime>
			<UnitDetail>"Unit Assigned"</UnitDetail></units><units>
			<UnitTime>"Jan 19 2022  8:37PM"</UnitTime>
			<UnitDetail>"Unit Cleared"</UnitDetail></units><units>
			<UnitTime>"Jan 19 2022  8:22PM"</UnitTime>
			<UnitDetail>"Unit At Scene"</UnitDetail></units><units>
			<UnitTime>"Jan 19 2022  8:16PM"</UnitTime>
			<UnitDetail>"Unit Enroute"</UnitDetail></units><units>
			<UnitTime>"Jan 19 2022  8:16PM"</UnitTime>
			<UnitDetail>"Unit Assigned"</UnitDetail></units><units>
			<UnitTime>"Jan 19 2022  8:15PM"</UnitTime>
			<UnitDetail>"Unit At Scene"</UnitDetail></units><units>
			<UnitTime>"Jan 19 2022  8:15PM"</UnitTime>
			<UnitDetail>"Unit Enroute"</UnitDetail></units><units>
			<UnitTime>"Jan 19 2022  8:15PM"</UnitTime>
			<UnitDetail>"Unit Assigned"</UnitDetail></units></LogDetails></Log>

		<Log ID = "220119BC01062">
			<LogTime>"Jan 19 2022  6:47PM"</LogTime>
			<LogType>"CZP-Assist with Construction"</LogType>
			<Location>"Sr74 / Hells Kitchen"</Location>
			<LocationDesc>"HELLS KITCHEN - COUNTY LINE"</LocationDesc>
			<Area>"Temecula"</Area>
			<ThomasBrothers>""</ThomasBrothers>
			<LATLON>"33646589:117417523"</LATLON>
			<LogDetails><details/><units>
			<UnitTime>"Jan 19 2022  8:23PM"</UnitTime>
			<UnitDetail>"Unit At Scene"</UnitDetail></units><units>
			<UnitTime>"Jan 19 2022  8:23PM"</UnitTime>
			<UnitDetail>"Unit Enroute"</UnitDetail></units><units>
			<UnitTime>"Jan 19 2022  7:03PM"</UnitTime>
			<UnitDetail>"Unit Assigned"</UnitDetail></units><units>
			<UnitTime>"Jan 19 2022  6:47PM"</UnitTime>
			<UnitDetail>"Unit At Scene"</UnitDetail></units><units>
			<UnitTime>"Jan 19 2022  6:47PM"</UnitTime>
			<UnitDetail>"Unit Enroute"</UnitDetail></units><units>
			<UnitTime>"Jan 19 2022  6:47PM"</UnitTime>
			<UnitDetail>"Unit Assigned"</UnitDetail></units></LogDetails></Log>

		<Log ID = "220119BC00846">
			<LogTime>"Jan 19 2022  4:00PM"</LogTime>
			<LogType>"SILVER Alert"</LogType>
			<Location>"Westminister"</Location>
			<LocationDesc>""</LocationDesc>
			<Area>""</Area>
			<ThomasBrothers>""</ThomasBrothers>
			<LATLON>"0:0"</LATLON>
			<LogDetails><details/></LogDetails></Log>
</Dispatch>
<Dispatch ID = "OCCC">

		<Log ID = "220120OC00019">
			<LogTime>"Jan 20 2022  1:24AM"</LogTime>
			<LogType>"1125-Traffic Hazard"</LogType>
			<Location>"Sr91 E Sr55 S Con / Sr55 S"</Location>
			<LocationDesc>"EB 91 JWO 55"</LocationDesc>
			<Area>"Santa Ana"</Area>
			<ThomasBrothers>""</ThomasBrothers>
			<LATLON>"33841850:117831152"</LATLON>
			<LogDetails>
		<details>
			<DetailTime>"Jan 20 2022  3:58AM"</DetailTime>
			<IncidentDetail>"[32] 1039 OCFA // CPYS ALL -- ENRT"</IncidentDetail>
		</details>
		<details>
			<DetailTime>"Jan 20 2022  3:32AM"</DetailTime>
			<IncidentDetail>"[30] [Notification] [CHP]-BT ETA 15 MINS "</IncidentDetail>
		</details>
		<details>
			<DetailTime>"Jan 20 2022  3:31AM"</DetailTime>
			<IncidentDetail>"[29] 1039 BT // CPYS ALL"</IncidentDetail>
		</details>
		<details>
			<DetailTime>"Jan 20 2022  2:08AM"</DetailTime>
			<IncidentDetail>"[23] [Notification] [CHP]-BT ETA 35 MINS"</IncidentDetail>
		</details>
		<details>
			<DetailTime>"Jan 20 2022  2:04AM"</DetailTime>
			<IncidentDetail>"[22] 1039 BT // CPYS ALL"</IncidentDetail>
		</details>
		<details>
			<DetailTime>"Jan 20 2022  1:47AM"</DetailTime>
			<IncidentDetail>"[17] [Rotation Request Comment] 1039 GEERS 714-524-2611"</IncidentDetail>
		</details>
		<details>
			<DetailTime>"Jan 20 2022  1:46AM"</DetailTime>
			<IncidentDetail>"[15] C86-405 * * * 1015 @ 0146 * * *  -  REQ 1185 FORD XPL"</IncidentDetail>
		</details>
		<details>
			<DetailTime>"Jan 20 2022  1:41AM"</DetailTime>
			<IncidentDetail>"[13] C86-405  ALL INSIDE CT CLOSURE - RDWY CLR"</IncidentDetail>
		</details>
		<details>
			<DetailTime>"Jan 20 2022  1:30AM"</DetailTime>
			<IncidentDetail>"[7] C86-571  HAS VEH TURNED OFF and STOPPED / DRIVER IS ASLEEP"</IncidentDetail>
		</details>
		<details>
			<DetailTime>"Jan 20 2022  1:29AM"</DetailTime>
			<IncidentDetail>"[6] C86-571  VEH BEHIND PV"</IncidentDetail>
		</details><units>
			<UnitTime>"Jan 20 2022  1:37AM"</UnitTime>
			<UnitDetail>"Unit At Scene"</UnitDetail></units><units>
			<UnitTime>"Jan 20 2022  1:30AM"</UnitTime>
			<UnitDetail>"Unit Enroute"</UnitDetail></units><units>
			<UnitTime>"Jan 20 2022  1:30AM"</UnitTime>
			<UnitDetail>"Unit Assigned"</UnitDetail></units><units>
			<UnitTime>"Jan 20 2022  2:17AM"</UnitTime>
			<UnitDetail>"Unit Cleared"</UnitDetail></units><units>
			<UnitTime>"Jan 20 2022  1:29AM"</UnitTime>
			<UnitDetail>"Unit At Scene"</UnitDetail></units><units>
			<UnitTime>"Jan 20 2022  1:29AM"</UnitTime>
			<UnitDetail>"Unit Enroute"</UnitDetail></units><units>
			<UnitTime>"Jan 20 2022  1:29AM"</UnitTime>
			<UnitDetail>"Unit Assigned"</UnitDetail></units><units>
			<UnitTime>"Jan 20 2022  1:29AM"</UnitTime>
			<UnitDetail>"Unit Cleared"</UnitDetail></units><units>
			<UnitTime>"Jan 20 2022  1:25AM"</UnitTime>
			<UnitDetail>"Unit Assigned"</UnitDetail></units></LogDetails></Log>

		<Log ID = "220120OC00003">
			<LogTime>"Jan 20 2022 12:00AM"</LogTime>
			<LogType>"CLOSURE of a Road"</LogType>
			<Location>"6681 Marine Way"</Location>
			<LocationDesc>"OCCC"</LocationDesc>
			<Area>"OC"</Area>
			<ThomasBrothers>""</ThomasBrothers>
			<LATLON>"33677582:117757184"</LATLON>
			<LogDetails><details/><units>
			<UnitTime>"Jan 20 2022 12:00AM"</UnitTime>
			<UnitDetail>"Unit At Scene"</UnitDetail></units><units>
			<UnitTime>"Jan 20 2022 12:00AM"</UnitTime>
			<UnitDetail>"Unit Enroute"</UnitDetail></units><units>
			<UnitTime>"Jan 20 2022 12:00AM"</UnitTime>
			<UnitDetail>"Unit Assigned"</UnitDetail></units></LogDetails></Log>

		<Log ID = "220120OC00002">
			<LogTime>"Jan 20 2022 12:00AM"</LogTime>
			<LogType>"1013-Road/Weather Conditions"</LogType>
			<Location>"6681 Marine Way"</Location>
			<LocationDesc>"OC MEDIA LOG"</LocationDesc>
			<Area>"OC"</Area>
			<ThomasBrothers>""</ThomasBrothers>
			<LATLON>"33677582:117757184"</LATLON>
			<LogDetails><details/><units>
			<UnitTime>"Jan 20 2022 12:00AM"</UnitTime>
			<UnitDetail>"Unit At Scene"</UnitDetail></units><units>
			<UnitTime>"Jan 20 2022 12:00AM"</UnitTime>
			<UnitDetail>"Unit Enroute"</UnitDetail></units><units>
			<UnitTime>"Jan 20 2022 12:00AM"</UnitTime>
			<UnitDetail>"Unit Assigned"</UnitDetail></units></LogDetails></Log>

		<Log ID = "220119OC00459">
			<LogTime>"Jan 19 2022 10:42PM"</LogTime>
			<LogType>"1179-Trfc Collision-1141 Enrt"</LogType>
			<Location>"SR91 E / SR55"</Location>
			<LocationDesc>"EB 91 AT 55"</LocationDesc>
			<Area>"Santa Ana"</Area>
			<ThomasBrothers>""</ThomasBrothers>
			<LATLON>"33844500:117828531"</LATLON>
			<LogDetails>
		<details>
			<DetailTime>"Jan 19 2022 11:05PM"</DetailTime>
			<IncidentDetail>"[39] C86-093  CT CREW SETTING UP CLOSURE FOR FT / WILL TRY TO ARRANGE FOR MAINLINES"</IncidentDetail>
		</details>
		<details>
			<DetailTime>"Jan 19 2022 11:01PM"</DetailTime>
			<IncidentDetail>"[37] PAC TOW CPYS"</IncidentDetail>
		</details>
		<details>
			<DetailTime>"Jan 19 2022 11:01PM"</DetailTime>
			<IncidentDetail>"[34] PACIFIC TOW REQ TO KNOW IF THEY CAN GO THRU CONES TO ACCESS FT"</IncidentDetail>
		</details>
		<details>
			<DetailTime>"Jan 19 2022 10:56PM"</DetailTime>
			<IncidentDetail>"[33] 1039 CONTROL"</IncidentDetail>
		</details>
		<details>
			<DetailTime>"Jan 19 2022 10:56PM"</DetailTime>
			<IncidentDetail>"[32] 77-M7 ISSUE 30 MIN SIG ALERT"</IncidentDetail>
		</details>
		<details>
			<DetailTime>"Jan 19 2022 10:56PM"</DetailTime>
			<IncidentDetail>"[31] C86-571 97 W/ BREAK @ KRAEMER"</IncidentDetail>
		</details>
		<details>
			<DetailTime>"Jan 19 2022 10:56PM"</DetailTime>
			<IncidentDetail>"[30] 77-M7 UNIT WILL NEED TO BLOCK ENTRANCE TO FT AS WELL AS #1/2 OF MAINLINES / TK IS W/IN 2 DIVIDER WALLS"</IncidentDetail>
		</details>
		<details>
			<DetailTime>"Jan 19 2022 10:52PM"</DetailTime>
			<IncidentDetail>"[29] [Rotation Request Comment] 1039 PACIFIC TOW 714-538-2001 W/ FB"</IncidentDetail>
		</details>
		<details>
			<DetailTime>"Jan 19 2022 10:52PM"</DetailTime>
			<IncidentDetail>"[28] 77-M7 START 1185 FB FOR FORD F15: PTYS OO VEH"</IncidentDetail>
		</details>
		<details>
			<DetailTime>"Jan 19 2022 10:50PM"</DetailTime>
			<IncidentDetail>"[17] 77-M7 WILL BE @ ENTRANCE TO THE FT LNS / THEY TC'D INTO ATTENUATORS"</IncidentDetail>
		</details>
		<details>
			<DetailTime>"Jan 19 2022 10:49PM"</DetailTime>
			<IncidentDetail>"[16] 77-M7 10-97"</IncidentDetail>
		</details><units>
			<UnitTime>"Jan 20 2022  5:23AM"</UnitTime>
			<UnitDetail>"Unit At Scene"</UnitDetail></units><units>
			<UnitTime>"Jan 20 2022  5:23AM"</UnitTime>
			<UnitDetail>"Unit Enroute"</UnitDetail></units><units>
			<UnitTime>"Jan 20 2022  5:23AM"</UnitTime>
			<UnitDetail>"Unit Assigned"</UnitDetail></units><units>
			<UnitTime>"Jan 20 2022  5:23AM"</UnitTime>
			<UnitDetail>"Unit Cleared"</UnitDetail></units><units>
			<UnitTime>"Jan 19 2022 11:52PM"</UnitTime>
			<UnitDetail>"Unit At Scene"</UnitDetail></units><units>
			<UnitTime>"Jan 19 2022 11:42PM"</UnitTime>
			<UnitDetail>"Unit Enroute"</UnitDetail></units><units>
			<UnitTime>"Jan 19 2022 11:42PM"</UnitTime>
			<UnitDetail>"Unit Assigned"</UnitDetail></units><units>
			<UnitTime>"Jan 20 2022  5:23AM"</UnitTime>
			<UnitDetail>"Unit Cleared"</UnitDetail></units><units>
			<UnitTime>"Jan 19 2022 11:05PM"</UnitTime>
			<UnitDetail>"Unit At Scene"</UnitDetail></units><units>
			<UnitTime>"Jan 19 2022 10:51PM"</UnitTime>
			<UnitDetail>"Unit Enroute"</UnitDetail></units><units>
			<UnitTime>"Jan 19 2022 10:51PM"</UnitTime>
			<UnitDetail>"Unit Assigned"</UnitDetail></units><units>
			<UnitTime>"Jan 20 2022  1:29AM"</UnitTime>
			<UnitDetail>"Unit Cleared"</UnitDetail></units><units>
			<UnitTime>"Jan 19 2022 11:06PM"</UnitTime>
			<UnitDetail>"Unit At Scene"</UnitDetail></units><units>
			<UnitTime>"Jan 19 2022 10:43PM"</UnitTime>
			<UnitDetail>"Unit Assigned"</UnitDetail></units></LogDetails></Log>
</Dispatch>
</Center>

</State>
